Workbook

Sheet Data Extraction
A1: Article ID | B1: Ryyan ID | C1: Dataset | D1: Papper | E1: DOI | F1: Titlle | G1: Year | H1: Objective of the Study (Researcher 1) | I1: Objective of the Study (AI Tool - OpenAI GPT) | J1: Objective of the Study (AI Tool - Anthropic Claude) | K1: Objective Codes (Researcher 1) | L1: Proposed Solution and Tracking Details (Researcher 1) | M1: Proposed Solution and Tracking Details (AI Tool - OpenAI GPT) | N1: Proposed Solution and Tracking Details (AI Tool - Anthropic Claude) | O1: What is being tracked? (Researcher 1) | P1: What is being tracked? (AI Tool - OpenAI GPT) | Q1: What is being tracked? (AI Tool - Anthropic Claude) | R1: Architecture Type (Researcher 1) | S1: Architecture Type (AI Tool - OpenAI GPT) | T1: Architecture Type (AI Tool - Anthropic Claude) | U1: Architecture Type | V1: Technology Stack (Researcher 1) | W1: Technology Stack (AI Tool - OpenAI GPT) | X1: Technology Stack (AI Tool - Anthropic Claude) | Y1: Purpose of Tracking (Researcher 1) | Z1: Purpose of Tracking (AI Tool - OpenAI GPT) | AA1: Purpose of Tracking (AI Tool - Anthropic Claude) | AB1: Responsibility Attribution (Researcher 1) | AC1: Responsibility Attribution (AI Tool - OpenAI GPT) | AD1: Responsibility Attribution (AI Tool - Anthropic Claude) | AE1: C1 (Researcher 1) | AF1: C1 - Value (AI Tool - OpenAI GPT) | AG1: C1 - Justification (AI Tool - OpenAI GPT) | AH1: C2 (Researcher 1) | AI1: C2 - Value (AI Tool - OpenAI GPT) | AJ1: C2 - Justification (AI Tool - OpenAI GPT) | AK1: C3 (Researcher 1) | AL1: C3 - Value (AI Tool - OpenAI GPT) | AM1: C3 - Justification (AI Tool - OpenAI GPT) | AN1: C4 (Researcher 1) | AO1: C4 - Value (AI Tool - OpenAI GPT) | AP1: C4 - Justification (AI Tool - OpenAI GPT) | AQ1: C5 (Researcher 1) | AR1: C5 - Value (AI Tool - OpenAI GPT) | AS1: C5 - Justification (AI Tool - OpenAI GPT) | AT1: C6 (Researcher 1) | AU1: C6 - Value (AI Tool - OpenAI GPT) | AV1: C6 - Justification (AI Tool - OpenAI GPT) | AW1: Research Method (Researcher 1) | AX1: Research Method (AI Tool - OpenAI GPT) | AY1: Evaluation Type (Researcher 1) | AZ1: Evaluation Type (AI Tool - OpenAI GPT) | BA1: Main Findings and Conclusions (Researcher 1) | BB1: Main Findings and Conclusions (AI Tool - OpenAI GPT) | BC1: Main Findings and Conclusions (AI Tool - Anthropic Claude) | BD1: Study Limitations (Researcher 1) | BE1: Study Limitations (AI Tool - OpenAI GPT) | BF1: Study Limitations (AI Tool - Anthropic Claude) | BG1: Notes (Researcher 1) | BH1: Notes (AI Tool - OpenAI GPT)
A2: 2-s2.0-84949513306 | B2: =VLOOKUP(A2,'Data Set'!A:C,2,FALSE) -> rayyan-172029219 | C2: =VLOOKUP(A2,'Data Set'!A:D,3,FALSE) -> 0 | D2: P001 | E2: 10.1109/ACSAC.2000.898877 | F2: Security Architectures for Controlled Digital Information Dissemination | G2: 2000 | H2: To identify and classify application-level security architectures that enable controlled dissemination and tracking of digital information, particularly in Payment-Free Type (PFT) environments. | I2: To identify and define security architectures that enable controlled dissemination and tracking of digital information, particularly in Payment-Free Type (PFT) environments, thereby providing a secure framework for organizations to manage digital content distribution. | J2: To identify and define security architectures that enable controlled dissemination and tracking of digital information, particularly in Payment-Free Type (PFT) environments, thereby providing a secure framework for organizations to manage digital content distribution. | K2: digital rights management, information dissemination control, tracking architectures, use-control, watermarking, security policy enforcement | L2: The article proposes eight distinct application-level security architectures based on three factors: Virtual Machine (VM), Control Set (CS), and Distribution Style. These architectures are designed to provide control and/or tracking capabilities for digital information dissemination. Tracking is achieved through watermarking and use-control technologies embedded in digital containers and enforced via virtual machines. | M2: The study addresses the domain of digital information security, focusing on the problem of unauthorized dissemination in Payment-Free Type environments. It proposes eight application-level security architectures based on three core elements: virtual machine, control set, and distribution style. These architectures vary in their ability to control and track digital information dissemination. The paper compares their capabilities, merits, and limitations, and discusses mechanisms such as watermarking and use-control technologies. A comparative analysis is provided by mapping commercial off-the-shelf solutions to the proposed architectures, demonstrating their practical relevance and availability. | N2: The study addresses the domain of digital information security, focusing on the problem of unauthorized dissemination in Payment-Free Type environments. It proposes eight application-level security architectures based on three core elements: virtual machine, control set, and distribution style. These architectures vary in their ability to control and track digital information dissemination. The paper compares their capabilities, merits, and limitations, and discusses mechanisms such as watermarking and use-control technologies. A comparative analysis is provided by mapping commercial off-the-shelf solutions to the proposed architectures, demonstrating their practical relevance and availability. | O2: Digital information (documents, media, technical descriptions) disseminated across organizations or systems. | P2: Digital information and its re-dissemination paths | Q2: Digital information and its re-dissemination paths | R2: Server-centered (most architectures rely on external repositories or control centers for access management) | S2: hybrid | T2: Server-centered | U2: =_xlfn.XLOOKUP(A2,ArticlesArchitecture[[#This Row],[Article ID]],ArticlesArchitecture[[#This Row],[Theme (final decision)]]) -> Server-centered | V2: Conceptual models using: virtual machines, digital containers, embedded/external control sets, watermarking technologies, and use-control mechanisms. No actual implementation is described; the paper presents a taxonomy and conceptual framework. | W2: The proposed solution integrates virtual machines, digital containers, control sets, and watermarking technologies. Virtual machines act as secure environments for accessing digital content, enforcing usage restrictions such as disabling print or save functions. Digital containers encapsulate content with cryptographic protections and usage policies. Control sets define access rights and can be embedded, external, or fixed. Watermarking technologies enable tracking by embedding invisible identifiers into digital content. The paper discusses actual implementations through commercial solutions like Adobe PDF Merchant and IBM Cryptolope, indicating a mix of conceptual and applied models. | X2: The proposed solution integrates virtual machines, digital containers, control sets, and watermarking technologies. Virtual machines act as secure environments for accessing digital content, enforcing usage restrictions such as disabling print or save functions. Digital containers encapsulate content with cryptographic protections and usage policies. Control sets define access rights and can be embedded, external, or fixed. Watermarking technologies enable tracking by embedding invisible identifiers into digital content. The paper discusses actual implementations through commercial solutions like Adobe PDF Merchant and IBM Cryptolope, indicating a mix of conceptual and applied models. | Y2: To prevent unauthorized redistribution of digital content and to trace the origin and path of re-disseminated information, ensuring confidentiality and accountability in sensitive environments such as intelligence and B2B transactions. | Z2: Tracking is necessary to identify unauthorized re-dissemination of digital information and to attribute responsibility. It aims to enhance security by enabling traceability of digital content, thereby deterring misuse and supporting forensic investigations. Tracking complements control mechanisms by providing post-distribution oversight, especially in environments where content may be leaked despite preventive measures. | AA2: Tracking is necessary to identify unauthorized re-dissemination of digital information and to attribute responsibility. It aims to enhance security by enabling traceability of digital content, thereby deterring misuse and supporting forensic investigations. Tracking complements control mechanisms by providing post-distribution oversight, especially in environments where content may be leaked despite preventive measures. | AB2: Yes. Watermarking mechanisms are proposed to embed identifiers (e.g., author, recipient, distribution date) into digital content, enabling tracing of unauthorized dissemination. | AC2: Yes, the architectures support responsibility attribution through watermarking mechanisms that embed sender and recipient identities into digital content, enabling tracing of re-dissemination events. | AD2: Yes, the architectures support responsibility attribution through watermarking mechanisms that embed sender and recipient identities into digital content, enabling tracing of re-dissemination events. | AE2: False. Justification: The paper presents conceptual architectures and mechanisms but does not describe any real-world implementation or deployment. | AF2: TRUE | AG2: The paper discusses commercial implementations of the proposed architectures, such as Adobe PDF Merchant and IBM Cryptolope. | AH2: True. Justification: The paper introduces a novel taxonomy of eight security architectures and integrates existing technologies (e.g., watermarking, use-control) into a unified framework. | AI2: TRUE | AJ2: The paper introduces a novel taxonomy of eight security architectures for digital information dissemination. | AK2: False. Justification: No empirical evaluation, case study, or experiment is conducted. | AL2: FALSE | AM2: There is no structured empirical evaluation or data analysis presented in the paper. | AN2: False. Justification: The architectures are not validated in industrial or organizational contexts. | AO2: FALSE | AP2: The paper does not report validation in industrial settings, although it references commercial tools. | AQ2: True. Justification: The paper presents a conceptual classification and framework without proposing a specific solution or implementation. | AR2: FALSE | AS2: The paper presents both conceptual models and references to implemented solutions, not solely a conceptual framework. | AT2: False. Justification: The paper is analytical and structured, not based on personal experience or anecdotal evidence. | AU2: FALSE | AV2: The paper is based on systematic analysis and architectural design, not solely on author opinions or experiences. | AW2: Solution proposal | AX2: Solution proposal | AY2: - | AZ2: - | BA2: The authors identify eight distinct security architectures for controlled digital information dissemination, each defined by combinations of virtual machine presence, control set type, and distribution style. They argue that these architectures can support both control and tracking capabilities, and propose watermarking and use-control mechanisms as essential technologies. The paper also maps existing commercial solutions to the proposed architectures. | BB2: The study identifies eight distinct security architectures for controlled digital information dissemination, each with varying capabilities for control and tracking. It emphasizes the importance of combining use-control and watermarking mechanisms to achieve comprehensive security. The architectures are mapped to existing commercial solutions, demonstrating their practical applicability. The paper concludes that these architectures provide a foundational framework for future research and development in secure digital content distribution. | BC2: The study identifies eight distinct security architectures for controlled digital information dissemination, each with varying capabilities for control and tracking. It emphasizes the importance of combining use-control and watermarking mechanisms to achieve comprehensive security. The architectures are mapped to existing commercial solutions, demonstrating their practical applicability. The paper concludes that these architectures provide a foundational framework for future research and development in secure digital content distribution. | BD2: No empirical validation or implementation is provided. The effectiveness of the proposed architectures and mechanisms is not tested. Watermarking technologies are acknowledged as immature and potentially vulnerable to tampering. | BE2: The paper acknowledges that watermarking technologies are still immature and may not reliably support tracking in all scenarios, especially if the content is tampered with. It also notes that embedding unique watermarks for mass dissemination is not yet feasible. | BF2: The paper acknowledges that watermarking technologies are still immature and may not reliably support tracking in all scenarios, especially if the content is tampered with. It also notes that embedding unique watermarks for mass dissemination is not yet feasible. | BG2: The paper emphasizes the need for generalized security architectures in PFT environments and provides a layered approach to understanding objectives, mechanisms, and architectures. It serves as a foundational taxonomy for future research and development in secure digital dissemination. | BH2: The article provides a foundational taxonomy and practical mapping of security architectures but lacks empirical validation or quantitative analysis.
A3: 2-s2.0-0242456750 | B3: =VLOOKUP(A3,'Data Set'!A:C,2,FALSE) -> rayyan-172029208 | C3: =VLOOKUP(A3,'Data Set'!A:D,3,FALSE) -> 0 | D3: P002 | E3: 10.1145/507721.507722 | F3: Towards Usage Control Models: Beyond Traditional Access Control | G3: 2002 | H3: To develop the concept of Usage Control (UCON), a unified model that integrates traditional access control, trust management, and digital rights management to address emerging security and privacy issues in digital environments. | I3: To introduce and formalize the concept of Usage Control (UCON), which unifies and extends traditional access control, trust management, and digital rights management into a comprehensive model for controlling access to and usage of digital information objects. | J3: To introduce and formalize the concept of Usage Control (UCON), which unifies and extends traditional access control, trust management, and digital rights management into a comprehensive model for controlling access to and usage of digital information objects. | K3: usage control, access control, trust management, digital rights management, privacy | L3: The article proposes the UCON model, which integrates server-side and client-side reference monitors to control usage of digital objects. It introduces components such as subjects, objects, rights, authorization rules, conditions, and obligations to enable fine-grained control over digital object usage. Tracking includes usage logs, payment information, and reverse usage control mechanisms. | M3: The study operates within the domain of information security, addressing the limitations of traditional access control, trust management, and digital rights management in handling modern security and privacy challenges. The authors propose the Usage Control (UCON) model, which integrates these three paradigms to enable fine-grained control over digital object usage, including rights delegation and post-access obligations. The model introduces core components—subjects, objects, and rights—and additional components such as authorization rules, conditions, and obligations. UCON supports both server-side and client-side reference monitors, as well as hybrid architectures, allowing for flexible enforcement in both centralized and decentralized environments. Comparative analysis demonstrates how UCON encompasses and extends existing models like Mandatory Access Control, Discretionary Access Control, Role-Based Access Control, and commercial Digital Rights Management systems. | N3: The study operates within the domain of information security, addressing the limitations of traditional access control, trust management, and digital rights management in handling modern security and privacy challenges. The authors propose the Usage Control (UCON) model, which integrates these three paradigms to enable fine-grained control over digital object usage, including rights delegation and post-access obligations. The model introduces core components—subjects, objects, and rights—and additional components such as authorization rules, conditions, and obligations. UCON supports both server-side and client-side reference monitors, as well as hybrid architectures, allowing for flexible enforcement in both centralized and decentralized environments. Comparative analysis demonstrates how UCON encompasses and extends existing models like Mandatory Access Control, Discretionary Access Control, Role-Based Access Control, and commercial Digital Rights Management systems. | O3: Usage logs, payment information, digital object access and modification rights | P3: Digital information objects and their derivative objects, including usage logs and payment information. | Q3: Digital information objects and their derivative objects, including usage logs and payment information. | R3: Hybrid (user-centered and server-centered) | S3: hybrid | T3: Server-centered | U3: =_xlfn.XLOOKUP(A3,ArticlesArchitecture[[#This Row],[Article ID]],ArticlesArchitecture[[#This Row],[Theme (final decision)]]) -> Hybrid (user-centered and server-centered) | W3: The article presents a conceptual model rather than an implemented system. It discusses the integration of traditional access control mechanisms (e.g., Mandatory Access Control, Discretionary Access Control, Role-Based Access Control), trust management systems, and Digital Rights Management technologies. The model incorporates server-side and client-side reference monitors, and introduces new components such as obligations and conditions for authorization. Technologies like access control lists, capability lists, and credit-based authorization are referenced, but no specific platforms, programming languages, or software frameworks are detailed. | X3: The article presents a conceptual model rather than an implemented system. It discusses the integration of traditional access control mechanisms (e.g., Mandatory Access Control, Discretionary Access Control, Role-Based Access Control), trust management systems, and Digital Rights Management technologies. The model incorporates server-side and client-side reference monitors, and introduces new components such as obligations and conditions for authorization. Technologies like access control lists, capability lists, and credit-based authorization are referenced, but no specific platforms, programming languages, or software frameworks are detailed. | Y3: To enforce usage policies, ensure privacy protection, support payment-based and payment-free dissemination, and enable accountability in digital environments. | Z3: Tracking is necessary to enforce fine-grained control over the usage of digital objects, including access, modification, and delegation of rights. It aims to address emerging security and privacy challenges in both commercial and non-commercial environments by enabling dynamic and context-aware authorization processes. Tracking supports the enforcement of obligations (e.g., usage logging, payment agreements) and conditions (e.g., time/location constraints), thereby enhancing accountability, privacy protection, and secure dissemination of digital content. | AA3: Tracking is necessary to enforce fine-grained control over the usage of digital objects, including access, modification, and delegation of rights. It aims to address emerging security and privacy challenges in both commercial and non-commercial environments by enabling dynamic and context-aware authorization processes. Tracking supports the enforcement of obligations (e.g., usage logging, payment agreements) and conditions (e.g., time/location constraints), thereby enhancing accountability, privacy protection, and secure dissemination of digital content. | AB3: Yes; the model allows identification of responsible parties through obligations and reverse UCON mechanisms, such as usage logs and payment records. | AC3: The UCON model includes mechanisms for tracking obligations and conditions, such as usage logs and payment information, which can be used to identify responsible parties in case of data leakage. The concept of reverse UCON further enables attribution by treating derivative objects (e.g., logs) as trackable entities with associated rights and obligations. | AD3: The UCON model includes mechanisms for tracking obligations and conditions, such as usage logs and payment information, which can be used to identify responsible parties in case of data leakage. The concept of reverse UCON further enables attribution by treating derivative objects (e.g., logs) as trackable entities with associated rights and obligations. | AE3: False. Justification: The model is not implemented or applied in a real-world setting. | AF3: FALSE | AG3: The paper presents a conceptual model without evidence of real-world implementation or deployment. | AH3: True. Justification: The paper introduces a novel unified model (UCON) integrating three distinct access control paradigms. | AI3: TRUE | AJ3: The paper introduces a novel model called Usage Control (UCON) that unifies and extends existing access control paradigms. | AK3: False. Justification: No empirical evaluation is conducted; the paper is conceptual. | AL3: FALSE | AM3: There is no structured empirical evaluation or data analysis presented in the article. | AN3: False. Justification: No industrial validation is presented. | AO3: FALSE | AP3: The model is not evaluated in an industrial context; examples are illustrative rather than based on industrial validation. | AQ3: True. Justification: The paper presents a conceptual framework without implementation or empirical validation. | AR3: FALSE | AS3: The paper goes beyond a conceptual framework by detailing model components and mapping to existing systems, though it remains theoretical. | AT3: False. Justification: The paper is not based on author opinion or personal experience but on theoretical synthesis. | AU3: FALSE | AV3: The paper is not based solely on the authors’ opinions or experiences; it builds on existing literature and proposes a structured model. | AW3: Philosophical paper | AX3: Solution proposal | AY3: - | AZ3: - | BA3: UCON provides a unified framework for usage control that surpasses traditional access control models by integrating trust management and digital rights management. It supports fine-grained control, hybrid architectures, and privacy-sensitive applications. The model introduces reverse usage control to handle derivative objects and emphasizes the need for legal or voluntary enforcement mechanisms. | BB3: The UCON model offers a unified and systematic approach to access and usage control by integrating traditional access control, trust management, and digital rights management. It introduces new components such as obligations and conditions, enabling finer-grained and context-aware authorization. The model supports hybrid architectures and addresses both security and privacy concerns. It lays the foundation for future research in delegation and administration within usage control systems. | BC3: The UCON model offers a unified and systematic approach to access and usage control by integrating traditional access control, trust management, and digital rights management. It introduces new components such as obligations and conditions, enabling finer-grained and context-aware authorization. The model supports hybrid architectures and addresses both security and privacy concerns. It lays the foundation for future research in delegation and administration within usage control systems. | BD3: The model lacks implementation and empirical validation. Delegation of rights and administrative aspects are identified as areas for future research. | BE3: The model is conceptual and lacks implementation details. Delegation of rights and administrative mechanisms are identified as areas requiring further research and development. | BF3: The model is conceptual and lacks implementation details. Delegation of rights and administrative mechanisms are identified as areas requiring further research and development. | BG3: The paper is foundational in proposing the UCON model and has influenced subsequent research in usage control and digital rights management. | BH3: The article is foundational in proposing the UCON model but does not include empirical validation or implementation. It is suitable for theoretical and conceptual analysis.
A4: 2-s2.0-65449181169 | B4: =VLOOKUP(A4,'Data Set'!A:C,2,FALSE) -> rayyan-218686268 | C4: =VLOOKUP(A4,'Data Set'!A:D,3,FALSE) -> Forward.1 | D4: P003 | E4: 10.1145/1409540.1409592 | F4: Preventing Information Leakage between Collaborating Organisations | G4: 2008 | H4: To propose a trusted computing-based framework for secure inter-organizational data sharing | I4: To propose a secure system that prevents information leakage when sensitive content is shared between collaborating organisations, ensuring that only authorised users within the destination organisation can access the shared content. | J4: To propose a secure system that prevents information leakage when sensitive content is shared between collaborating organisations, ensuring that only authorised users within the destination organisation can access the shared content. | K4: trusted computing, enterprise rights management, data leakage prevention | L4: A domain-based access control model using TPM, trusted software agents, and master controllers | M4: The study addresses the problem of information leakage during inter-organisational collaboration, particularly when sensitive data is shared across organisational boundaries. The authors propose a novel solution that integrates trusted computing technologies to enforce access control and data protection. The system introduces the concept of global and dynamic domains, where devices are grouped and assigned cryptographic keys to restrict access to shared content. A master controller manages domain membership and enforces organisational policies. Comparative analysis with existing access control models highlights the limitations of traditional approaches and the advantages of the proposed system in preventing both internal and external data leakage. | N4: The study addresses the problem of information leakage during inter-organisational collaboration, particularly when sensitive data is shared across organisational boundaries. The authors propose a novel solution that integrates trusted computing technologies to enforce access control and data protection. The system introduces the concept of global and dynamic domains, where devices are grouped and assigned cryptographic keys to restrict access to shared content. A master controller manages domain membership and enforces organisational policies. Comparative analysis with existing access control models highlights the limitations of traditional approaches and the advantages of the proposed system in preventing both internal and external data leakage. | O4: Sensitive organizational content | P4: Sensitive organisational content and access credentials | Q4: Sensitive organisational content and access credentials | R4: Server-centered | S4: server-centered | T4: Server-centered | U4: =_xlfn.XLOOKUP(A4,ArticlesArchitecture[[#This Row],[Article ID]],ArticlesArchitecture[[#This Row],[Theme (final decision)]]) -> Server-centered | V4: Trusted Platform Module (TPM), TCG specs, domain keys, master controller; conceptual model only | W4: The proposed solution is built upon Trusted Computing Group (TCG) specifications, incorporating Trusted Platform Modules (TPMs) for secure storage and attestation. Trusted software agents are deployed on organisational devices and master controllers to enforce access policies and manage cryptographic keys. The system uses sealed storage, attestation identity keys, and mutual authentication protocols to ensure that only trusted devices and software environments can access protected content. The implementation is conceptual, with detailed descriptions of protocols and workflows, but no empirical deployment is reported. | X4: The proposed solution is built upon Trusted Computing Group (TCG) specifications, incorporating Trusted Platform Modules (TPMs) for secure storage and attestation. Trusted software agents are deployed on organisational devices and master controllers to enforce access policies and manage cryptographic keys. The system uses sealed storage, attestation identity keys, and mutual authentication protocols to ensure that only trusted devices and software environments can access protected content. The implementation is conceptual, with detailed descriptions of protocols and workflows, but no empirical deployment is reported. | Y4: To prevent internal and external leakage during inter-organizational sharing | Z4: Tracking is necessary to ensure that sensitive content shared between organisations is only accessible to authorised users and devices. It aims to prevent both accidental and intentional data leakage by enforcing strict access control policies and verifying the integrity of devices and software environments. This contributes to the broader goal of secure information sharing in collaborative settings. | AA4: Tracking is necessary to ensure that sensitive content shared between organisations is only accessible to authorised users and devices. It aims to prevent both accidental and intentional data leakage by enforcing strict access control policies and verifying the integrity of devices and software environments. This contributes to the broader goal of secure information sharing in collaborative settings. | AB4: Yes; domain keys and TPM binding enable traceability | AC4: Yes, the system enables identification of responsible parties through logging mechanisms and device-specific access control. Logs are stored in protected environments and can record sender identity, device IP, recipient details, and timestamps, which can be used to trace data access and potential leakage. | AD4: Yes, the system enables identification of responsible parties through logging mechanisms and device-specific access control. Logs are stored in protected environments and can record sender identity, device IP, recipient details, and timestamps, which can be used to trace data access and potential leakage. | AE4: False. No real-world implementation. | AF4: FALSE | AG4: The paper does not report a real-world deployment or application of the proposed system. | AH4: True. Novel domain-based access control model. | AI4: TRUE | AJ4: The paper introduces a novel solution integrating trusted computing for inter-organisational data protection. | AK4: False. No empirical evaluation. | AL4: FALSE | AM4: There is no structured data collection or empirical evaluation presented. | AN4: False. No industrial validation. | AO4: FALSE | AP4: The solution is not validated in an industrial context. | AQ4: True. Conceptual framework only. | AR4: FALSE | AS4: The paper presents a detailed conceptual model but also includes implementation-level details. | AT4: False. Not based on author experience. | AU4: FALSE | AV4: The paper is not based solely on author experience or opinion. | AW4: Opinion paper | AX4: Solution proposal | AY4: - | AZ4: - | BA4: The framework outlines a secure sharing model using trusted computing and domain keys | BB4: The proposed system effectively addresses the challenge of preventing information leakage between collaborating organisations by using trusted computing technologies. It introduces global and dynamic domains to control access and enforces organisational policies through a master controller. The system ensures that only authorised users can access shared content and that data cannot be leaked to unauthorised parties, even within the destination organisation. | BC4: The proposed system effectively addresses the challenge of preventing information leakage between collaborating organisations by using trusted computing technologies. It introduces global and dynamic domains to control access and enforces organisational policies through a master controller. The system ensures that only authorised users can access shared content and that data cannot be leaked to unauthorised parties, even within the destination organisation. | BD4: No implementation or empirical validation | BE4: The paper does not include empirical validation or real-world deployment of the proposed system. Implementation details are conceptual, and integration with existing authentication mechanisms is noted as outside the scope of the study. | BF4: The paper does not include empirical validation or real-world deployment of the proposed system. Implementation details are conceptual, and integration with existing authentication mechanisms is noted as outside the scope of the study. | BG4: Suggests future integration with monitoring and detection systems | BH4: The article provides a comprehensive conceptual framework for secure inter-organisational data sharing but lacks empirical evaluation or industrial validation.
A5: 2-s2.0-84864275237 | B5: =VLOOKUP(A5,'Data Set'!A:C,2,FALSE) -> rayyan-172029019 | C5: =VLOOKUP(A5,'Data Set'!A:D,3,FALSE) -> 0 | D5: P004 | E5: 10.1109/SPW.2012.19 | F5: Fog Computing: Mitigating Insider Data Theft Attacks in the Cloud | G5: 2012 | H5: To propose a novel approach for securing cloud data against insider threats using Fog computing, which combines user behavior profiling and decoy information to detect and mitigate unauthorized access. | I5: To propose a novel approach for securing data in cloud environments against insider threats by using decoy-based disinformation techniques integrated with user behavior profiling. | J5: To propose a novel approach for securing data in cloud environments against insider threats by using decoy-based disinformation techniques integrated with user behavior profiling. | K5: cloud security, insider threat detection, decoy technology, user behavior profiling | L5: The article proposes a security mechanism that monitors user behavior in the cloud to detect abnormal access patterns. Upon suspicion of unauthorized access, challenge questions are used for verification. If confirmed, a disinformation attack is launched by serving decoy data to the attacker. This approach integrates user behavior profiling and decoy document deployment to protect sensitive data. | M5: The study addresses the problem of insider data theft in cloud computing, a critical concern for businesses outsourcing data storage and computation. The authors propose a solution termed 'Fog Computing', which integrates offensive decoy technology and user behavior profiling to detect and mitigate unauthorized access. The system monitors access patterns and, upon detecting anomalies, verifies legitimacy through challenge questions. If access is deemed unauthorized, it launches a disinformation attack by delivering decoy data to the attacker. This approach is compared against traditional encryption and access control methods, which have proven insufficient. Experimental results in local file systems suggest that combining behavior profiling with decoy deployment significantly enhances detection accuracy and security. | N5: The study addresses the problem of insider data theft in cloud computing, a critical concern for businesses outsourcing data storage and computation. The authors propose a solution termed 'Fog Computing', which integrates offensive decoy technology and user behavior profiling to detect and mitigate unauthorized access. The system monitors access patterns and, upon detecting anomalies, verifies legitimacy through challenge questions. If access is deemed unauthorized, it launches a disinformation attack by delivering decoy data to the attacker. This approach is compared against traditional encryption and access control methods, which have proven insufficient. Experimental results in local file systems suggest that combining behavior profiling with decoy deployment significantly enhances detection accuracy and security. | O5: User access patterns and interactions with cloud-stored data, including search behavior and file access. | P5: User access patterns and interactions with data files, including decoy documents. | Q5: User access patterns and interactions with data files, including decoy documents. | R5: Server-centered | S5: user-centered | T5: User-centered | U5: =_xlfn.XLOOKUP(A5,ArticlesArchitecture[[#This Row],[Article ID]],ArticlesArchitecture[[#This Row],[Theme (final decision)]]) -> Server-centered | V5: Conceptual model using one-class support vector machines for behavior profiling, decoy document generation with HMAC verification, and integration of profiling with decoy deployment. No full implementation in cloud; experiments conducted in local file system. | W5: The proposed solution utilizes user behavior profiling through one-class support vector machines to model normal access patterns. Decoy documents are embedded with keyed-Hash Message Authentication Codes (HMACs) to verify authenticity and detect unauthorized access. These decoys are strategically placed in conspicuous directories and named enticingly to attract potential attackers. The system does not rely on real-time decoy generation but emphasizes conspicuous placement and integration with anomaly detection. The implementation is demonstrated in a local file system setting, suggesting applicability to cloud environments. | X5: The proposed solution utilizes user behavior profiling through one-class support vector machines to model normal access patterns. Decoy documents are embedded with keyed-Hash Message Authentication Codes (HMACs) to verify authenticity and detect unauthorized access. These decoys are strategically placed in conspicuous directories and named enticingly to attract potential attackers. The system does not rely on real-time decoy generation but emphasizes conspicuous placement and integration with anomaly detection. The implementation is demonstrated in a local file system setting, suggesting applicability to cloud environments. | Y5: To detect and prevent unauthorized access to sensitive cloud data, especially by malicious insiders, by identifying abnormal user behavior and triggering decoy-based disinformation responses. | Z5: Tracking is employed to detect abnormal access behaviors indicative of insider threats. By profiling legitimate user behavior and monitoring interactions with decoy files, the system aims to identify masqueraders and prevent data exfiltration. The tracking supports challenge-response mechanisms and enables the deployment of disinformation to protect sensitive data. | AA5: Tracking is employed to detect abnormal access behaviors indicative of insider threats. By profiling legitimate user behavior and monitoring interactions with decoy files, the system aims to identify masqueraders and prevent data exfiltration. The tracking supports challenge-response mechanisms and enables the deployment of disinformation to protect sensitive data. | AB5: Yes. The system uses challenge questions and behavior profiling to validate user identity and detect impersonation, allowing attribution of unauthorized access to masqueraders. | AC5: The approach does not explicitly attribute responsibility for data leakage but enables detection of unauthorized access through behavioral anomalies and decoy interaction, which may indirectly support attribution. | AD5: The approach does not explicitly attribute responsibility for data leakage but enables detection of unauthorized access through behavioral anomalies and decoy interaction, which may indirectly support attribution. | AE5: False. Justification: The proposed solution was tested in a local file system environment, not deployed in a real-world cloud setting. | AF5: TRUE | AG5: Experiments were conducted in a local file system setting to simulate real-world scenarios. | AH5: True. Justification: The paper introduces a novel integration of decoy technology and user behavior profiling for cloud security. | AI5: TRUE | AJ5: The paper introduces a novel concept called Fog Computing combining decoy technology and user profiling. | AK5: True. Justification: Experiments were conducted using simulated masquerader data and user models trained on real usage data. | AL5: TRUE | AM5: Structured experiments were performed using user data and simulated attacks. | AN5: False. Justification: No evidence of evaluation in an industrial or organizational context. | AO5: FALSE | AP5: No evidence of industrial validation or deployment in commercial cloud environments. | AQ5: False. Justification: The paper proposes and evaluates a concrete solution, not just a conceptual framework. | AR5: FALSE | AS5: The paper presents an implemented and tested approach, not just a conceptual framework. | AT5: False. Justification: The study is based on experimental data and not solely on author opinion or experience. | AU5: FALSE | AV5: The study is based on empirical data and not solely on author experience or opinion. | AW5: Validation research | AX5: Evaluation research | AY5: Laboratory experiment (machine or human) | AZ5: Controlled experiment with practitioners | BA5: The combination of user behavior profiling and decoy technology significantly improves the detection of masquerade attacks. The approach can effectively confuse attackers and protect sensitive data, suggesting its potential applicability in cloud environments. | BB5: Combining user behavior profiling with decoy technology significantly improves the detection of masquerade attacks. The approach reduces false positives and enhances security by confusing attackers and validating alerts. The results suggest that this method could be effectively applied in cloud environments. | BC5: Combining user behavior profiling with decoy technology significantly improves the detection of masquerade attacks. The approach reduces false positives and enhances security by confusing attackers and validating alerts. The results suggest that this method could be effectively applied in cloud environments. | BD5: The solution was only tested in a local file system, not in an actual cloud environment. Decoys were pre-generated rather than dynamically created at detection time. | BE5: The experiments were conducted in a local file system setting, not in actual cloud environments. Real-time decoy generation was not implemented, and industrial validation is lacking. | BF5: The experiments were conducted in a local file system setting, not in actual cloud environments. Real-time decoy generation was not implemented, and industrial validation is lacking. | BG5: The study was supported by DARPA under the ADAMS and MRC programs. The authors suggest future work to implement the approach in real cloud systems. | BH5: The paper is a position paper supported by DARPA and includes references to prior technical reports and experiments.
A6: 2-s2.0-84918536488 | B6: =VLOOKUP(A6,'Data Set'!A:C,2,FALSE) -> rayyan-172029046 | C6: =VLOOKUP(A6,'Data Set'!A:D,3,FALSE) -> 0 | D6: P005 | E6: 10.1109/MEC.2013.6885474 | F6: A Distribution Model for Data Leakage Prevention | G6: 2013 | H6: To present a file distribution model that minimizes data leakage by considering user guilt probability | I6: To propose a file distribution model that minimizes data leakage by incorporating user guilt probability into the allocation strategy. | J6: To propose a file distribution model that minimizes data leakage by incorporating user guilt probability into the allocation strategy. | K6: data leakage prevention, cloud security, trust management | L6: A file allocation strategy that minimizes overlap in file sets among users, using guilt probability to identify potential leakers | M6: The study addresses the problem of sensitive data leakage in cloud computing environments. It proposes a distribution model that integrates user guilt probability—a metric indicating the likelihood of a user leaking data—into the file allocation strategy. The model aims to minimize the overlap of file sets among users, thereby enhancing the ability to trace the source of data leakage. Compared to previous models, this approach improves the accuracy of identifying malicious users and enhances information security through simulation-based validation. | N6: The study addresses the problem of sensitive data leakage in cloud computing environments. It proposes a distribution model that integrates user guilt probability—a metric indicating the likelihood of a user leaking data—into the file allocation strategy. The model aims to minimize the overlap of file sets among users, thereby enhancing the ability to trace the source of data leakage. Compared to previous models, this approach improves the accuracy of identifying malicious users and enhances information security through simulation-based validation. | O6: Sensitive files in cloud environments | P6: Sensitive data files distributed to users | Q6: Sensitive data files distributed to users | R6: Server-centered | S6: server-centered | T6: Server-centered | U6: =_xlfn.XLOOKUP(A6,ArticlesArchitecture[[#This Row],[Article ID]],ArticlesArchitecture[[#This Row],[Theme (final decision)]]) -> Server-centered | V6: Conceptual model using guilt probability, simulation-based validation; no implementation stack specified | W6: The proposed solution is conceptual and algorithmic in nature. It includes a multi-round file distribution strategy that uses guilt probability metrics to guide allocation decisions. The system comprises algorithms such as FirstDis, NextDis, DistOneDis, and MinimumSum, which collectively determine optimal file distribution plans. The model is implemented and validated through simulation experiments, but no specific programming languages, platforms, or frameworks are mentioned, indicating a conceptual rather than a fully implemented system. | X6: The proposed solution is conceptual and algorithmic in nature. It includes a multi-round file distribution strategy that uses guilt probability metrics to guide allocation decisions. The system comprises algorithms such as FirstDis, NextDis, DistOneDis, and MinimumSum, which collectively determine optimal file distribution plans. The model is implemented and validated through simulation experiments, but no specific programming languages, platforms, or frameworks are mentioned, indicating a conceptual rather than a fully implemented system. | Y6: To identify malicious users and prevent further leakage | Z6: Tracking is employed to identify potential sources of data leakage by analyzing the distribution of sensitive files and calculating user guilt probabilities. This enables the system to distinguish between honest, common, and malicious users, thereby supporting preventive measures and enhancing data security. | AA6: Tracking is employed to identify potential sources of data leakage by analyzing the distribution of sensitive files and calculating user guilt probabilities. This enables the system to distinguish between honest, common, and malicious users, thereby supporting preventive measures and enhancing data security. | AB6: Yes; based on guilt probability model | AC6: Yes, the model enables identification of responsible parties through the guilt probability metric, which helps infer the likelihood of a user being the source of a data leak. | AD6: Yes, the model enables identification of responsible parties through the guilt probability metric, which helps infer the likelihood of a user being the source of a data leak. | AE6: False. No real-world implementation. | AF6: FALSE | AG6: The model is validated through simulation experiments, not applied in a real-world setting. | AH6: True. Novel guilt-based model. | AI6: TRUE | AJ6: The paper introduces a novel distribution model incorporating guilt probability for data leakage prevention. | AK6: True. Simulation-based evaluation. | AL6: TRUE | AM6: Structured simulation experiments are conducted to evaluate the model's effectiveness. | AN6: False. No industrial validation. | AO6: FALSE | AP6: There is no evidence of industrial validation; the evaluation is limited to simulations. | AQ6: False. Not philosophical. | AR6: FALSE | AS6: The paper presents a detailed algorithmic model and simulation results, not just a conceptual framework. | AT6: False. Not based on author experience. | AU6: FALSE | AV6: The study is based on algorithmic development and simulation, not solely on author experience or opinion. | AW6: Validation research | AX6: Validation research | AY6: Simulation as an empirical method | AZ6: Simulation | BA6: The model effectively distinguishes malicious users and identifies leak sources with high probability | BB6: The proposed distribution model effectively identifies malicious users by leveraging guilt probability. Simulation results show that incorporating guilt probability increases the differentiation between user types, thereby improving the accuracy of leak source detection and enhancing data security. | BC6: The proposed distribution model effectively identifies malicious users by leveraging guilt probability. Simulation results show that incorporating guilt probability increases the differentiation between user types, thereby improving the accuracy of leak source detection and enhancing data security. | BD6: No real-world deployment; simulation only | BE6: The model is tested only in simulated environments; practical deployment and real-world validation are not addressed. | BF6: The model is tested only in simulated environments; practical deployment and real-world validation are not addressed. | BG6: Guilt probability enhances traceability in cloud file distribution | BH6: The article provides a simulation-based validation of a conceptual model. No implementation details such as programming languages or platforms are provided.
A7: 2-s2.0-84942810277 | B7: =VLOOKUP(A7,'Data Set'!A:C,2,FALSE) -> rayyan-218688840 | C7: =VLOOKUP(A7,'Data Set'!A:D,3,FALSE) -> Backward.1 | D7: P006 | E7: 10.1049/cje.2015.10.033 | F7: EABDS: Attribute-Based Secure Data Sharing with Efficient Revocation in Cloud Computing | G7: 2015 | H7: To propose an attribute-based encryption scheme with efficient revocation and escrow-free key management for cloud data sharing. | I7: To propose a secure data sharing scheme in cloud computing that ensures data confidentiality, efficient revocation, and fine-grained access control using attribute-based encryption. | J7: To propose a secure data sharing scheme in cloud computing that ensures data confidentiality, efficient revocation, and fine-grained access control using attribute-based encryption. | K7: cloud security, attribute-based encryption, key revocation, access control | L7: EABDS encrypts data using CP-ABE and DEK, with homomorphic encryption for key generation. Revocation is handled via key server updates and ciphertext re-encryption. | M7: The study addresses the problem of secure data sharing in cloud computing, particularly focusing on data confidentiality, access control, and key escrow issues. It introduces the EABDS scheme, which combines symmetric encryption with Ciphertext-Policy Attribute-Based Encryption (CP-ABE) to protect data. The scheme uses additively homomorphic encryption to collaboratively generate attribute secret keys by the attribute authority and key server, thereby mitigating the key escrow problem. It also incorporates an immediate attribute revocation mechanism that ensures both forward and backward security. Comparative analysis shows that EABDS reduces computational overhead on users and improves security and efficiency compared to existing schemes. | N7: The study addresses the problem of secure data sharing in cloud computing, particularly focusing on data confidentiality, access control, and key escrow issues. It introduces the EABDS scheme, which combines symmetric encryption with Ciphertext-Policy Attribute-Based Encryption (CP-ABE) to protect data. The scheme uses additively homomorphic encryption to collaboratively generate attribute secret keys by the attribute authority and key server, thereby mitigating the key escrow problem. It also incorporates an immediate attribute revocation mechanism that ensures both forward and backward security. Comparative analysis shows that EABDS reduces computational overhead on users and improves security and efficiency compared to existing schemes. | O7: Encrypted cloud data (DEK and CP-ABE ciphertexts) | P7: Data encryption keys and user attributes for access control | Q7: Data encryption keys and user attributes for access control | R7: Server-centered | S7: hybrid | T7: Server-centered | U7: =_xlfn.XLOOKUP(A7,ArticlesArchitecture[[#This Row],[Article ID]],ArticlesArchitecture[[#This Row],[Theme (final decision)]]) -> Server-centered | V7: CP-ABE, homomorphic encryption, bilinear maps, symmetric encryption | W7: The proposed solution integrates symmetric encryption for data protection and Ciphertext-Policy Attribute-Based Encryption (CP-ABE) for access control. It employs additively homomorphic encryption to enable collaborative key generation between the attribute authority and key server, preventing any single entity from accessing the full attribute secret keys. The system uses bilinear maps and elliptic curve cryptography, implemented via a pairing-based cryptography library. The architecture is practically implemented and simulated on a virtual machine using Ubuntu 12.10, demonstrating its computational efficiency. | X7: The proposed solution integrates symmetric encryption for data protection and Ciphertext-Policy Attribute-Based Encryption (CP-ABE) for access control. It employs additively homomorphic encryption to enable collaborative key generation between the attribute authority and key server, preventing any single entity from accessing the full attribute secret keys. The system uses bilinear maps and elliptic curve cryptography, implemented via a pairing-based cryptography library. The architecture is practically implemented and simulated on a virtual machine using Ubuntu 12.10, demonstrating its computational efficiency. | Y7: To ensure fine-grained access control, forward/backward secrecy, and prevent key escrow in cloud environments. | Z7: Tracking is necessary to enforce fine-grained access control, ensure data confidentiality, and support secure revocation of user attributes. It enables the system to determine whether a user possesses the required attributes to decrypt data, thereby preventing unauthorized access and ensuring that revoked users cannot access past or future data. | AA7: Tracking is necessary to enforce fine-grained access control, ensure data confidentiality, and support secure revocation of user attributes. It enables the system to determine whether a user possesses the required attributes to decrypt data, thereby preventing unauthorized access and ensuring that revoked users cannot access past or future data. | AB7: Yes. Malicious entities can be identified via access control logs and key server records. | AC7: Yes, the scheme enables identification of responsible parties in case of data leakage by ensuring that attribute secret keys are uniquely generated for each user through collaboration between the attribute authority and key server. | AD7: Yes, the scheme enables identification of responsible parties in case of data leakage by ensuring that attribute secret keys are uniquely generated for each user through collaboration between the attribute authority and key server. | AE7: True. Scheme implemented and tested. | AF7: TRUE | AG7: The scheme is implemented and simulated in a virtual environment using real cryptographic libraries. | AH7: True. Novel escrow-free CP-ABE with revocation. | AI7: TRUE | AJ7: The paper introduces a novel scheme (EABDS) combining CP-ABE with homomorphic encryption for secure data sharing. | AK7: True. Performance and security analysis conducted. | AL7: TRUE | AM7: The paper includes performance simulations comparing encryption and decryption times with existing schemes. | AN7: False. No industrial deployment. | AO7: FALSE | AP7: There is no evidence of evaluation in an industrial context; the validation is academic. | AQ7: False. Not conceptual only. | AR7: FALSE | AS7: The paper presents a fully constructed and implemented solution, not just a conceptual framework. | AT7: False. Not based on personal experience. | AU7: FALSE | AV7: The paper is based on technical implementation and analysis, not solely on author experience or opinion. | AW7: Evaluation research | AX7: Evaluation research | AY7: Mathematical analysis and proof of properties | AZ7: Simulation | BA7: EABDS achieves secure, efficient, and revocable data sharing with reduced user overhead and strong privacy guarantees. | BB7: The EABDS scheme effectively addresses key escrow and attribute revocation challenges in cloud computing. It ensures data confidentiality, supports fine-grained access control, and reduces computational overhead on users by delegating decryption tasks to a key server. Compared to existing schemes, EABDS offers improved security and efficiency. | BC7: The EABDS scheme effectively addresses key escrow and attribute revocation challenges in cloud computing. It ensures data confidentiality, supports fine-grained access control, and reduces computational overhead on users by delegating decryption tasks to a key server. Compared to existing schemes, EABDS offers improved security and efficiency. | BD7: No real-world deployment; simulation-based validation only. | BE7: The scheme assumes semi-trusted entities and does not address scenarios where the attribute authority and key server collude. It also excludes protection for data after successful decryption by users. | BF7: The scheme assumes semi-trusted entities and does not address scenarios where the attribute authority and key server collude. It also excludes protection for data after successful decryption by users. | BG7: Compared against existing schemes for revocation and escrow. | BH7: The article provides a detailed construction and simulation of the proposed scheme, making it suitable for practical application in secure cloud data sharing.
A8: 2-s2.0-84988963251 | B8: =VLOOKUP(A8,'Data Set'!A:C,2,FALSE) -> rayyan-172028983 | C8: =VLOOKUP(A8,'Data Set'!A:D,3,FALSE) -> 0 | D8: P007 | E8: 10.1109/ICONSTEM.2016.7560956 | F8: Mitigating Insider Data Theft Attacks in the Cloud | G8: 2016 | H8: To propose a novel approach for securing cloud data against insider threats using decoy information and user behavior profiling. | I8: To propose a novel approach for securing data in cloud environments against insider threats by combining user behavior profiling and decoy information technologies. | J8: To propose a novel approach for securing data in cloud environments against insider threats by combining user behavior profiling and decoy information technologies. | K8: cloud security, data theft prevention, user behavior profiling, decoy technology, fog computing | L8: The study introduces a dual-layer security mechanism combining user behavior profiling and decoy information (Fog computing). It monitors access patterns and launches disinformation attacks when unauthorized access is detected, returning decoy data to confuse attackers. | M8: The study addresses the problem of insider data theft in cloud computing, a critical concern for businesses outsourcing data storage and computation. The authors propose a solution based on 'Fog computing', which integrates user behavior profiling and decoy information technologies. This approach monitors data access patterns to detect anomalies and responds to suspected unauthorized access by deploying decoy documents. These decoys serve both as detection mechanisms and as a means to confuse attackers, thereby protecting real user data. Comparative experiments conducted in a local file system setting demonstrate that combining these techniques improves detection accuracy and reduces false positives, suggesting potential effectiveness in cloud environments. | N8: The study addresses the problem of insider data theft in cloud computing, a critical concern for businesses outsourcing data storage and computation. The authors propose a solution based on 'Fog computing', which integrates user behavior profiling and decoy information technologies. This approach monitors data access patterns to detect anomalies and responds to suspected unauthorized access by deploying decoy documents. These decoys serve both as detection mechanisms and as a means to confuse attackers, thereby protecting real user data. Comparative experiments conducted in a local file system setting demonstrate that combining these techniques improves detection accuracy and reduces false positives, suggesting potential effectiveness in cloud environments. | O8: User access patterns and file search behavior in cloud environments. | P8: User data access patterns and interactions with decoy documents. | Q8: User data access patterns and interactions with decoy documents. | R8: Server-centered | S8: user-centered | T8: User-centered | U8: =_xlfn.XLOOKUP(A8,ArticlesArchitecture[[#This Row],[Article ID]],ArticlesArchitecture[[#This Row],[Theme (final decision)]]) -> Server-centered | V8: Conceptual model using Fog computing, decoy documents with embedded HMACs, and one-class support vector machines for behavior profiling. Implementation tested in local file systems, not in actual cloud environments. | W8: The proposed solution utilizes user behavior profiling through one-class support vector machines to model normal access patterns and detect anomalies. Decoy documents are generated and embedded with keyed Hash Message Authentication Codes (HMACs) to validate unauthorized access. These decoys are strategically placed in conspicuous directories and named enticingly to attract potential attackers. The system does not rely on real-time decoy generation but uses pre-deployed traps. The implementation is demonstrated in a local file system environment, suggesting a conceptual model with experimental validation rather than a full-scale cloud deployment. | X8: The proposed solution utilizes user behavior profiling through one-class support vector machines to model normal access patterns and detect anomalies. Decoy documents are generated and embedded with keyed Hash Message Authentication Codes (HMACs) to validate unauthorized access. These decoys are strategically placed in conspicuous directories and named enticingly to attract potential attackers. The system does not rely on real-time decoy generation but uses pre-deployed traps. The implementation is demonstrated in a local file system environment, suggesting a conceptual model with experimental validation rather than a full-scale cloud deployment. | Y8: To detect and prevent unauthorized access by malicious insiders and masqueraders by identifying abnormal user behavior and triggering decoy responses. | Z8: Tracking is employed to detect and mitigate unauthorized access to cloud-stored data, particularly by malicious insiders. By profiling user behavior and monitoring interactions with decoy documents, the system aims to identify masquerade attacks. Upon detection, it launches disinformation attacks to protect sensitive data, thereby enhancing security and reducing the impact of data breaches. | AA8: Tracking is employed to detect and mitigate unauthorized access to cloud-stored data, particularly by malicious insiders. By profiling user behavior and monitoring interactions with decoy documents, the system aims to identify masquerade attacks. Upon detection, it launches disinformation attacks to protect sensitive data, thereby enhancing security and reducing the impact of data breaches. | AB8: Yes. The system uses challenge questions and HMAC verification to validate access and identify unauthorized users. | AC8: The approach does not explicitly enable identification of the responsible party in case of data leakage. It focuses on detecting unauthorized access and mitigating its impact rather than attributing responsibility. | AD8: The approach does not explicitly enable identification of the responsible party in case of data leakage. It focuses on detecting unauthorized access and mitigating its impact rather than attributing responsibility. | AE8: False. Justification: The solution was tested in a local file system, not deployed in a real-world cloud environment. | AF8: TRUE | AG8: The techniques were applied in a local file system setting to simulate real-world scenarios. | AH8: True. Justification: Introduces a new combination of decoy technology and user profiling for cloud security. | AI8: TRUE | AJ8: The paper introduces a novel combination of user behavior profiling and decoy technology for cloud security. | AK8: True. Justification: Experiments were conducted using simulated masquerader data and classifiers trained on user behavior. | AL8: TRUE | AM8: Structured experiments were conducted using classifiers trained on user data to evaluate detection accuracy. | AN8: False. Justification: No evidence of evaluation in an industrial or organizational setting. | AO8: FALSE | AP8: There is no indication that the solution was evaluated in an industrial context. | AQ8: False. Justification: The paper proposes and evaluates a concrete solution. | AR8: FALSE | AS8: The paper presents experimental results, not just a conceptual framework. | AT8: False. Justification: The study is based on experimental data, not personal opinion. | AU8: FALSE | AV8: The study is based on empirical data and not solely on author opinions or experiences. | AW8: Validation research | AX8: Evaluation research | AY8: Laboratory experiment (machine or human) | AZ8: Laboratory experiment | BA8: The combined use of user behavior profiling and decoy technology significantly improves detection of masquerade attacks. The approach reduces false positives and enhances cloud data security. | BB8: The combination of user behavior profiling and decoy technology significantly improves the detection of masquerade attacks. The approach yields low false positive rates and enhances security by confusing attackers with bogus data. The results suggest that this method could be effective in cloud environments. | BC8: The combination of user behavior profiling and decoy technology significantly improves the detection of masquerade attacks. The approach yields low false positive rates and enhances security by confusing attackers with bogus data. The results suggest that this method could be effective in cloud environments. | BD8: The solution was only tested in a local file system, not in actual cloud environments. Real-world applicability and scalability remain unverified. | BE8: The experiments were conducted in a local file system setting, not in a real cloud environment. The decoys were pre-deployed rather than generated on demand, which may affect real-world applicability. | BF8: The experiments were conducted in a local file system setting, not in a real cloud environment. The decoys were pre-deployed rather than generated on demand, which may affect real-world applicability. | BG8: The concept of Fog computing is introduced as a disinformation strategy. The study is supported by DARPA under the ADAMS and MRC programs. | BH8: The article proposes a promising security mechanism but lacks industrial validation and real cloud deployment.
A9: 2-s2.0-84991717011 | B9: =VLOOKUP(A9,'Data Set'!A:C,2,FALSE) -> rayyan-218688824 | C9: =VLOOKUP(A9,'Data Set'!A:D,3,FALSE) -> Backward.1 | D9: P008 | E9: 10.1109/OBD.2016.11 | F9: MedRec: Using Blockchain for Medical Data Access and Permission Management | G9: 2016 | H9: To develop a decentralized EMR management system using blockchain to improve patient agency, data access, and interoperability. | I9: To propose and demonstrate a decentralized record management system for electronic medical records using blockchain technology, aimed at improving access, interoperability, and patient agency in healthcare data management. | J9: To propose and demonstrate a decentralized record management system for electronic medical records using blockchain technology, aimed at improving access, interoperability, and patient agency in healthcare data management. | K9: blockchain, EMR, smart contracts, data sharing, data economics | L9: MedRec uses Ethereum smart contracts to manage patient-provider relationships, access permissions, and data integrity. Patients control access via cryptographic keys and receive notifications of updates. | M9: The article introduces MedRec, a decentralized system for managing electronic medical records using blockchain technology. The business domain is healthcare, where the problem addressed is the fragmented, inefficient, and opaque management of medical data across providers. The proposed solution leverages Ethereum-based smart contracts to manage data ownership, access permissions, and integrity, enabling patients to control and share their medical records securely. The system integrates with existing provider databases through modular APIs, ensuring interoperability. A novel incentive mechanism involving blockchain mining is introduced, where researchers and healthcare authorities can mine blocks in exchange for access to anonymized aggregate data. This approach is compared to prior art, highlighting MedRec’s unique contribution as a fully functional prototype in contrast to conceptual models like Factom and MedVault. | N9: The article introduces MedRec, a decentralized system for managing electronic medical records using blockchain technology. The business domain is healthcare, where the problem addressed is the fragmented, inefficient, and opaque management of medical data across providers. The proposed solution leverages Ethereum-based smart contracts to manage data ownership, access permissions, and integrity, enabling patients to control and share their medical records securely. The system integrates with existing provider databases through modular APIs, ensuring interoperability. A novel incentive mechanism involving blockchain mining is introduced, where researchers and healthcare authorities can mine blocks in exchange for access to anonymized aggregate data. This approach is compared to prior art, highlighting MedRec’s unique contribution as a fully functional prototype in contrast to conceptual models like Factom and MedVault. | O9: Electronic Medical Records (EMRs) | P9: Electronic medical records and associated metadata, including ownership, access permissions, and data integrity hashes. | Q9: Electronic medical records and associated metadata, including ownership, access permissions, and data integrity hashes. | R9: User-centered | S9: hybrid | T9: User-centered | U9: =_xlfn.XLOOKUP(A9,ArticlesArchitecture[[#This Row],[Article ID]],ArticlesArchitecture[[#This Row],[Theme (final decision)]]) -> User-centered | V9: Ethereum blockchain, smart contracts, Python Flask, SQLite, PyEthereum | W9: The developed solution is implemented using Ethereum blockchain technology, specifically leveraging smart contracts for permission management and data integrity. The system includes components such as a Backend Library for blockchain interaction, an Ethereum Client for network participation, a Database Gatekeeper for off-chain data access, and an EMR Manager for user interface and data visualization. The prototype integrates with SQLite databases and uses Flask for the web interface, ensuring compatibility with mobile devices. The architecture supports modular interoperability with existing EMR systems and facilitates secure, decentralized data management. | X9: The developed solution is implemented using Ethereum blockchain technology, specifically leveraging smart contracts for permission management and data integrity. The system includes components such as a Backend Library for blockchain interaction, an Ethereum Client for network participation, a Database Gatekeeper for off-chain data access, and an EMR Manager for user interface and data visualization. The prototype integrates with SQLite databases and uses Flask for the web interface, ensuring compatibility with mobile devices. The architecture supports modular interoperability with existing EMR systems and facilitates secure, decentralized data management. | Y9: To enable secure, auditable, and patient-controlled access to EMRs across providers and researchers. | Z9: Tracking is necessary to provide patients with a comprehensive, immutable log of their medical history, enable secure and auditable data sharing across providers, and support medical research through access to anonymized aggregate data. It aims to restore patient agency, improve interoperability, and facilitate data-driven healthcare innovations while maintaining confidentiality and compliance with regulations. | AA9: Tracking is necessary to provide patients with a comprehensive, immutable log of their medical history, enable secure and auditable data sharing across providers, and support medical research through access to anonymized aggregate data. It aims to restore patient agency, improve interoperability, and facilitate data-driven healthcare innovations while maintaining confidentiality and compliance with regulations. | AB9: Yes. Access logs and permissioning are stored on-chain, enabling auditability. | AC9: Yes, the system enables identification of responsible parties through cryptographic signatures and blockchain-based logging of transactions. Each data access or modification is recorded immutably, allowing for accountability and auditability in case of data leakage or unauthorized access. | AD9: Yes, the system enables identification of responsible parties through cryptographic signatures and blockchain-based logging of transactions. Each data access or modification is recorded immutably, allowing for accountability and auditability in case of data leakage or unauthorized access. | AE9: True. A working prototype is implemented. | AF9: TRUE | AG9: The article presents a working prototype of the MedRec system and discusses its implementation and integration with existing EMR infrastructure. | AH9: True. Novel use of smart contracts for EMR access. | AI9: TRUE | AJ9: The paper introduces a novel blockchain-based solution for managing electronic medical records, including original smart contract designs and incentive models. | AK9: True. Functional prototype tested with simulated data. | AL9: FALSE | AM9: The article does not include structured data collection or empirical analysis; it focuses on system design and prototype demonstration. | AN9: False. No industrial deployment. | AO9: FALSE | AP9: There is no evidence of evaluation in an industrial context; the system has not yet undergone field testing. | AQ9: False. Not conceptual only. | AR9: FALSE | AS9: The paper presents a functional prototype rather than a purely conceptual framework. | AT9: False. Not based on personal experience. | AU9: FALSE | AV9: The article is based on technical implementation rather than solely on author opinions or experiences. | AW9: Evaluation research | AX9: Solution proposal | AY9: Prototyping | AZ9: - | BA9: MedRec provides decentralized, patient-controlled EMR access with auditability and incentives for researchers via data mining rewards. | BB9: MedRec demonstrates how blockchain technology can be applied to electronic medical records to enhance auditability, interoperability, and patient control. The system enables secure data sharing, supports medical research through incentivized mining, and integrates with existing healthcare infrastructure. It offers a decentralized approach to data management, reducing reliance on centralized systems and improving resilience. | BC9: MedRec demonstrates how blockchain technology can be applied to electronic medical records to enhance auditability, interoperability, and patient control. The system enables secure data sharing, supports medical research through incentivized mining, and integrates with existing healthcare infrastructure. It offers a decentralized approach to data management, reducing reliance on centralized systems and improving resilience. | BD9: Scalability and privacy-preserving query construction not fully addressed. | BE9: The system does not address the security of individual databases or digital rights management. Scalability remains a challenge for blockchain implementations, and privacy concerns related to pseudonymous transactions require further exploration. Future work includes user studies and privacy-preserving query construction. | BF9: The system does not address the security of individual databases or digital rights management. Scalability remains a challenge for blockchain implementations, and privacy concerns related to pseudonymous transactions require further exploration. Future work includes user studies and privacy-preserving query construction. | BG9: Introduces data economics via anonymized mining incentives. | BH9: The article presents a pioneering application of blockchain in healthcare, with a strong emphasis on patient empowerment and data economics. It provides a detailed technical description of the system components and their interactions.
A10: 2-s2.0-85006364680 | B10: =VLOOKUP(A10,'Data Set'!A:C,2,FALSE) -> rayyan-172028976 | C10: =VLOOKUP(A10,'Data Set'!A:D,3,FALSE) -> 0 | D10: P009 | E10: n/a | F10: A Secure Multi‐Layer e‐Application Framework for e‐Government Processes | G10: 2014 | H10: To propose a secure multi-layer e-application framework (SMeAF) for structuring e-documents in e-government systems, aiming to improve data flexibility, security, and interoperability. | I10: To propose a secure multi-layer E-Application framework (SMeAF) that enhances the structuring and security of E-Documents within e-Government systems, particularly focusing on improving data flexibility, interoperability, and protection in developing countries. | J10: To propose a secure multi-layer E-Application framework (SMeAF) that enhances the structuring and security of E-Documents within e-Government systems, particularly focusing on improving data flexibility, interoperability, and protection in developing countries. | K10: e-Government, data security, XML integration, digital signature, document tracking, citizen-centric design | L10: The study introduces SMeAF, a three-layer framework comprising a data layer (citizen and agency data), a control layer (task execution, timing, tracking), and a security layer (XML Security Criterion Expression and e-Signature). It enables secure structuring, sharing, and tracking of e-documents across government agencies. | M10: The study addresses the challenges of E-Document design and secure data sharing in e-Government systems, particularly in developing countries. It introduces the Secure Multi-layer E-Application Framework (SMeAF), which structures E-Documents into three distinct layers: data, control, and security. The framework aims to reduce database size and processing time, facilitate data reuse and sharing among government agencies, and enable citizens to track their application status. The security layer incorporates XML Security Criterion Expression and E-Signature methodologies to ensure confidentiality, integrity, authenticity, non-repudiation, availability, proof of agreement, and proof of existence. A case study involving a Vietnamese citizen applying for a business license demonstrates the framework’s practical application and comparative advantages over existing models. | N10: The study addresses the challenges of E-Document design and secure data sharing in e-Government systems, particularly in developing countries. It introduces the Secure Multi-layer E-Application Framework (SMeAF), which structures E-Documents into three distinct layers: data, control, and security. The framework aims to reduce database size and processing time, facilitate data reuse and sharing among government agencies, and enable citizens to track their application status. The security layer incorporates XML Security Criterion Expression and E-Signature methodologies to ensure confidentiality, integrity, authenticity, non-repudiation, availability, proof of agreement, and proof of existence. A case study involving a Vietnamese citizen applying for a business license demonstrates the framework’s practical application and comparative advantages over existing models. | O10: E-Documents submitted by citizens, including personal, business, financial, and tax data, and their processing status across government agencies. | P10: Citizen-submitted E-Applications, including personal data, business information, financial reports, and tax data, as well as the status and history of these applications throughout the e-Government process. | Q10: Citizen-submitted E-Applications, including personal data, business information, financial reports, and tax data, as well as the status and history of these applications throughout the e-Government process. | R10: User-centered | S10: hybrid | T10: User-centered | U10: =_xlfn.XLOOKUP(A10,ArticlesArchitecture[[#This Row],[Article ID]],ArticlesArchitecture[[#This Row],[Theme (final decision)]]) -> Hybrid (user-centered and server-centered) | V10: XML/XML Schema, XML Security Criterion Expression (SCE), SHA-256 hash function, ElGamal digital signature scheme. The solution is implemented and demonstrated through a case study involving Vietnamese government licensing. | W10: The proposed solution is implemented using XML and XML schema for data structuring and integration. The framework employs XML Security Criterion Expression (SCE) to define access control rules and E-Signature techniques based on the ElGamal signature scheme for data integrity and authentication. The system uses SHA-256 for hashing XML documents and applies a multilayer architecture to manage data flow and security. The implementation includes a case study with real XML files and digital signatures exchanged between government agencies, indicating a practical deployment of the conceptual model. | X10: The proposed solution is implemented using XML and XML schema for data structuring and integration. The framework employs XML Security Criterion Expression (SCE) to define access control rules and E-Signature techniques based on the ElGamal signature scheme for data integrity and authentication. The system uses SHA-256 for hashing XML documents and applies a multilayer architecture to manage data flow and security. The implementation includes a case study with real XML files and digital signatures exchanged between government agencies, indicating a practical deployment of the conceptual model. | Y10: To allow citizens and agencies to monitor the status and history of e-applications, ensure secure data exchange, and support evaluation and approval processes. | Z10: Tracking is essential to monitor the status and history of E-Applications submitted by citizens, ensuring transparency and accountability in the e-Government process. It allows citizens to verify the progress of their applications, supports agency assessments, and facilitates secure data exchange. Tracking also contributes to data integrity and helps prevent unauthorized access or modifications, thereby enhancing trust in the system. | AA10: Tracking is essential to monitor the status and history of E-Applications submitted by citizens, ensuring transparency and accountability in the e-Government process. It allows citizens to verify the progress of their applications, supports agency assessments, and facilitates secure data exchange. Tracking also contributes to data integrity and helps prevent unauthorized access or modifications, thereby enhancing trust in the system. | AB10: Yes. The framework uses XML security expressions and digital signatures to authenticate data origin and integrity, enabling identification of responsible parties in case of data leakage. | AC10: Yes, the framework enables identification of responsible parties through the use of E-Signatures and tracking mechanisms. Each agency’s tasks are time-stamped and digitally signed, allowing for verification of actions and accountability in case of data leakage or disputes. | AD10: Yes, the framework enables identification of responsible parties through the use of E-Signatures and tracking mechanisms. Each agency’s tasks are time-stamped and digitally signed, allowing for verification of actions and accountability in case of data leakage or disputes. | AE10: True. Justification: The framework was applied in a real-world case study involving the Vietnamese government’s business licensing process. | AF10: TRUE | AG10: The framework is applied in a real-world case study involving a citizen applying for a business license with the Vietnamese Government. | AH10: True. Justification: The paper introduces a new multi-layer framework (SMeAF) combining XML security and digital signatures for e-government applications. | AI10: TRUE | AJ10: The paper introduces a novel Secure Multi-layer E-Application Framework (SMeAF) for structuring and securing E-Documents. | AK10: True. Justification: The framework was evaluated through a detailed case study with timing, tracking, and security validation. | AL10: TRUE | AM10: Structured data collection and analysis are presented through XML schema, digital signatures, and timing evaluations in the case study. | AN10: True. Justification: The solution was validated in the context of a government agency (Vietnamese licensing process). | AO10: FALSE | AP10: Although the framework is applied in a governmental context, there is no formal industrial validation or evaluation reported. | AQ10: False. Justification: The paper includes implementation and empirical validation, not just conceptual discussion. | AR10: FALSE | AS10: The paper presents a practical implementation with a case study, not just a conceptual framework. | AT10: False. Justification: The study is based on a structured framework and empirical case study, not personal opinion. | AU10: FALSE | AV10: The study is based on structured methodology and technical implementation, not solely on author opinions or experiences. | AW10: Evaluation research | AX10: Evaluation research | AY10: Industrial case study | AZ10: Industrial case study | BA10: The proposed SMeAF framework improves the structuring, security, and interoperability of e-documents in e-government systems. It enables efficient data sharing, tracking, and secure communication between citizens and agencies. The case study demonstrated reduced processing time and enhanced data protection. | BB10: The Secure Multi-layer E-Application Framework (SMeAF) improves the structuring and security of E-Documents in e-Government systems. It enhances data integration, reduces processing time, and ensures secure data exchange through XML-based security expressions and digital signatures. The case study demonstrates the framework’s effectiveness in streamlining administrative processes and improving citizen engagement. | BC10: The Secure Multi-layer E-Application Framework (SMeAF) improves the structuring and security of E-Documents in e-Government systems. It enhances data integration, reduces processing time, and ensures secure data exchange through XML-based security expressions and digital signatures. The case study demonstrates the framework’s effectiveness in streamlining administrative processes and improving citizen engagement. | BD10: The study is limited to a single case study in Vietnam; broader applicability across different governmental contexts is not evaluated. | BE10: The paper does not provide quantitative performance metrics or comparative analysis with other frameworks in terms of efficiency or scalability. Industrial validation is limited to a single case study without broader empirical testing. | BF10: The paper does not provide quantitative performance metrics or comparative analysis with other frameworks in terms of efficiency or scalability. Industrial validation is limited to a single case study without broader empirical testing. | BG10: The framework integrates XML-based security and digital signatures to meet seven security goals (confidentiality, integrity, authenticity, non-repudiation, availability, proof of agreement, proof of existence). It supports citizen tracking and agency evaluation processes. | BH10: The article provides a detailed technical implementation of the proposed framework, including XML schema examples and digital signature algorithms. However, it lacks broader empirical validation across multiple government contexts.
A11: 2-s2.0-85015367281 | B11: =VLOOKUP(A11,'Data Set'!A:C,2,FALSE) -> rayyan-218686026 | C11: =VLOOKUP(A11,'Data Set'!A:D,3,FALSE) -> Forward.1 | D11: P010 | E11: 10.1109/GLOCOM.2016.7841554 | F11: A System for Detecting Malicious Insider Data Theft in IaaS Cloud Environments | G11: 2016 | H11: To propose and evaluate a system for detecting malicious insider data theft in IaaS cloud environments using k-nearest neighbors anomaly detection. | I11: To propose and evaluate a system for detecting malicious insider data theft in Infrastructure as a Service (IaaS) cloud environments using a train-monitor-detect pattern based on k-nearest neighbors anomaly detection and system state data. | J11: To propose and evaluate a system for detecting malicious insider data theft in Infrastructure as a Service (IaaS) cloud environments using a train-monitor-detect pattern based on k-nearest neighbors anomaly detection and system state data. | K11: cloud security, insider threat, data theft detection, IaaS, anomaly detection, digital forensics | L11: A train-monitor-detect system in which agents installed on cloud nodes collect system metrics (logins, network transmission) and state data (open files, connections), sent to a central detector that uses stateful rule-based k-NN anomaly detection and provides forensic evidence. | M11: The study addresses the problem of malicious insider data theft in the domain of cloud computing, specifically within Infrastructure as a Service (IaaS) environments. The authors propose a proactive security system that employs a train-monitor-detect pattern using a stateful rule-based k-nearest neighbors anomaly detection technique. The system monitors system metrics such as active user counts and network transmission data, alongside system state information like open files and network connections, to identify unauthorized data extraction activities. The solution is instantiated on the Eucalyptus cloud infrastructure and demonstrates a 100% detection rate for abnormal login events and data transfers to external systems, with zero false positives when all detection conditions are met. | N11: The study addresses the problem of malicious insider data theft in the domain of cloud computing, specifically within Infrastructure as a Service (IaaS) environments. The authors propose a proactive security system that employs a train-monitor-detect pattern using a stateful rule-based k-nearest neighbors anomaly detection technique. The system monitors system metrics such as active user counts and network transmission data, alongside system state information like open files and network connections, to identify unauthorized data extraction activities. The solution is instantiated on the Eucalyptus cloud infrastructure and demonstrates a 100% detection rate for abnormal login events and data transfers to external systems, with zero false positives when all detection conditions are met. | O11: IaaS cloud node activity: active user logins, TCP bytes sent, open files and network connections. | P11: Active user logins, network transmission data (TCP bytes sent), open files, and network connections on IaaS cloud nodes. | Q11: Active user logins, network transmission data (TCP bytes sent), open files, and network connections on IaaS cloud nodes. | R11: Server-centered | S11: server-centered | T11: Server-centered | U11: =_xlfn.XLOOKUP(A11,ArticlesArchitecture[[#This Row],[Article ID]],ArticlesArchitecture[[#This Row],[Theme (final decision)]]) -> Server-centered | V11: Eucalyptus IaaS cloud, IBM InfoSphere Streams, SPL, Python agents (psutil, netstat), UDP sockets, k-nearest neighbors; implemented and tested | W11: The developed solution is implemented in a real-world IaaS cloud environment using the Eucalyptus cloud infrastructure and IBM InfoSphere Streams. Agents written in Python are deployed on cloud nodes to collect system metrics and forensic data using the psutil package and netstat. Data is transmitted via UDP sockets to a central detector system. The detector is implemented using Python and Streams Processing Language (SPL). It operates in two modes: training and monitoring. During training, anomaly scores are calculated and stored in JSON format. During monitoring, incoming data is enriched with trained anomaly thresholds and analyzed in real-time. Alerts are generated when anomalies exceed thresholds and forensic evidence supports the detection. The system is fully implemented and tested in a physical cloud environment consisting of five multi-core systems connected via Gigabit Ethernet. | X11: The developed solution is implemented in a real-world IaaS cloud environment using the Eucalyptus cloud infrastructure and IBM InfoSphere Streams. Agents written in Python are deployed on cloud nodes to collect system metrics and forensic data using the psutil package and netstat. Data is transmitted via UDP sockets to a central detector system. The detector is implemented using Python and Streams Processing Language (SPL). It operates in two modes: training and monitoring. During training, anomaly scores are calculated and stored in JSON format. During monitoring, incoming data is enriched with trained anomaly thresholds and analyzed in real-time. Alerts are generated when anomalies exceed thresholds and forensic evidence supports the detection. The system is fully implemented and tested in a physical cloud environment consisting of five multi-core systems connected via Gigabit Ethernet. | Y11: To detect insider data theft by rogue administrators and provide forensic data for investigation | Z11: Tracking is necessary to detect and prevent insider data theft in IaaS cloud environments, particularly from rogue administrators. The objective is to identify abnormal login activities and unauthorized data transfers that may indicate malicious intent. By monitoring system metrics and forensic data, the system aims to provide real-time alerts and forensic evidence to support investigations and enhance cloud security through a defense-in-depth strategy. | AA11: Tracking is necessary to detect and prevent insider data theft in IaaS cloud environments, particularly from rogue administrators. The objective is to identify abnormal login activities and unauthorized data transfers that may indicate malicious intent. By monitoring system metrics and forensic data, the system aims to provide real-time alerts and forensic evidence to support investigations and enhance cloud security through a defense-in-depth strategy. | AB11: Yes. Logs of abnormal logins and data transfers and forensic data (IP addresses, accessed files) allow identification of the responsible party. | AC11: Yes, the approach enables identification of the responsible party in case of data leakage. The system logs abnormal login events and data transfers, and collects forensic data such as IP addresses and file access information, which can be used to attribute responsibility. | AD11: Yes, the approach enables identification of the responsible party in case of data leakage. The system logs abnormal login events and data transfers, and collects forensic data such as IP addresses and file access information, which can be used to attribute responsibility. | AE11: True. Implemented and evaluated in a real IaaS cloud environment (Eucalyptus). | AF11: TRUE | AG11: The system is instantiated and evaluated in a real-world IaaS cloud environment using Eucalyptus infrastructure. | AH11: True. Novel train-monitor-detect approach for insider data theft detection. | AI11: TRUE | AJ11: The paper introduces a novel train-monitor-detect system using k-nearest neighbors anomaly detection for insider data theft detection. | AK11: True. Structured experiments with 48 attack scenarios. | AL11: TRUE | AM11: Structured experimentation was conducted with 48 attack scenarios and 233,829 data sets to evaluate detection performance. | AN11: False. Evaluated in a research cloud, not an industrial production setting. | AO11: FALSE | AP11: The evaluation was conducted in a research cloud environment, not in an industrial production setting. | AQ11: False. Not philosophical; implemented system. | AR11: FALSE | AS11: The paper presents a fully implemented and evaluated system, not just a conceptual framework. | AT11: False. Not based on author opinion or experience. | AU11: FALSE | AV11: The study is based on empirical experimentation rather than solely on author opinions or experiences. | AW11: Evaluation research | AX11: Evaluation research | AY11: Laboratory experiment (machine) | AZ11: Prototyping | BA11: 100% detection rate with zero false positives when login anomalies, data transfer anomalies and forensic evidence are combined; robust across IaaS states and workloads. | BB11: The proposed system achieved a 100% detection rate for insider data theft attacks with zero false positives when login anomalies, data transfer anomalies, and forensic evidence were all present. The system was effective across various IaaS states and workloads, demonstrating its robustness and practical applicability. | BC11: The proposed system achieved a 100% detection rate for insider data theft attacks with zero false positives when login anomalies, data transfer anomalies, and forensic evidence were all present. The system was effective across various IaaS states and workloads, demonstrating its robustness and practical applicability. | BD11: Scalability in large-scale IaaS environments not tested; single indicators alone produced false positives. | BE11: The system's scalability in large-scale IaaS environments was not tested. Additionally, the use of single detection events (login, data transfer, or forensic data alone) resulted in false positives or unreliable detection, indicating the necessity of combining multiple indicators. | BF11: The system's scalability in large-scale IaaS environments was not tested. Additionally, the use of single detection events (login, data transfer, or forensic data alone) resulted in false positives or unreliable detection, indicating the necessity of combining multiple indicators. | BG11: Defense-in-depth approach focusing on rogue administrators; forensic evidence supports investigations. | BH11: The article provides a comprehensive implementation and evaluation of a novel insider data theft detection system. It includes detailed descriptions of the architecture, technology stack, and experimental setup.
A12: 2-s2.0-85028950622 | B12: =VLOOKUP(A12,'Data Set'!A:C,2,FALSE) -> rayyan-218688578 | C12: =VLOOKUP(A12,'Data Set'!A:D,3,FALSE) -> Backward.1 | D12: P011 | E12: 10.1109/ACCESS.2017.2730843 | F12: MeDShare: Trust-Less Medical Data Sharing Among Cloud Service Providers via Blockchain | G12: 2017 | H12: To design a blockchain-based framework for secure, auditable, and trust-less sharing of medical data among cloud service providers. | I12: To propose a blockchain-based system, MeDShare, that enables secure, trust-less sharing of medical data among cloud service providers while ensuring data provenance, auditing, and access control. | J12: To propose a blockchain-based system, MeDShare, that enables secure, trust-less sharing of medical data among cloud service providers while ensuring data provenance, auditing, and access control. | K12: blockchain, cloud computing, data provenance, access control, smart contracts | L12: MeDShare uses smart contracts and side-blocks to monitor data access and violations. Actions are logged immutably, and access is revoked upon breach. | M12: The study addresses the healthcare domain, focusing on the problem of securely sharing electronic medical records among untrusted cloud service providers. The proposed solution, MeDShare, is a blockchain-based system that ensures data provenance, auditing, and access control through smart contracts and cryptographic mechanisms. It tracks all actions performed on shared data and revokes access upon detecting violations. The system is designed to operate in a trust-less environment and is evaluated against existing solutions, demonstrating comparable performance while enhancing security and traceability. | N12: The study addresses the healthcare domain, focusing on the problem of securely sharing electronic medical records among untrusted cloud service providers. The proposed solution, MeDShare, is a blockchain-based system that ensures data provenance, auditing, and access control through smart contracts and cryptographic mechanisms. It tracks all actions performed on shared data and revokes access upon detecting violations. The system is designed to operate in a trust-less environment and is evaluated against existing solutions, demonstrating comparable performance while enhancing security and traceability. | O12: Medical data shared across cloud repositories | P12: Electronic medical records and all actions performed on them during and after sharing. | Q12: Electronic medical records and all actions performed on them during and after sharing. | R12: Server-centered | S12: server-centered | T12: Server-centered | U12: =_xlfn.XLOOKUP(A12,ArticlesArchitecture[[#This Row],[Article ID]],ArticlesArchitecture[[#This Row],[Theme (final decision)]]) -> Server-centered | V12: Blockchain (unspecified platform), smart contracts, side-blocks, audit logs | W12: The solution is implemented using blockchain technology with smart contracts written in Solidity. It includes a layered architecture with components such as a query system, triggers, authenticators, processing and consensus nodes, and a smart contract permissioned database. Cryptographic primitives are used for secure communication, including requestor private/public keys and authenticator contract keys. The system is implemented and tested using JMeter for performance evaluation, indicating a functional prototype rather than a purely conceptual model. | X12: The solution is implemented using blockchain technology with smart contracts written in Solidity. It includes a layered architecture with components such as a query system, triggers, authenticators, processing and consensus nodes, and a smart contract permissioned database. Cryptographic primitives are used for secure communication, including requestor private/public keys and authenticator contract keys. The system is implemented and tested using JMeter for performance evaluation, indicating a functional prototype rather than a purely conceptual model. | Y12: To enable secure data sharing with provenance and accountability across untrusted cloud entities. | Z12: Tracking is necessary to ensure data provenance, auditing, and secure access control in a trust-less environment. It aims to detect and respond to unauthorized actions on medical data, revoke access upon violations, and maintain an immutable log of all interactions. This contributes to mitigating privacy risks and enhancing accountability in medical data sharing among cloud service providers. | AA12: Tracking is necessary to ensure data provenance, auditing, and secure access control in a trust-less environment. It aims to detect and respond to unauthorized actions on medical data, revoke access upon violations, and maintain an immutable log of all interactions. This contributes to mitigating privacy risks and enhancing accountability in medical data sharing among cloud service providers. | AB12: Yes. Violations trigger access revocation and are logged immutably. | AC12: Yes, the system enables identification of responsible parties through the use of cryptographic identities (requestor ID, data owner ID) and smart contracts that log and report violations. These logs are stored in a permissioned database and appended to blockchain side-blocks for traceability. | AD12: Yes, the system enables identification of responsible parties through the use of cryptographic identities (requestor ID, data owner ID) and smart contracts that log and report violations. These logs are stored in a permissioned database and appended to blockchain side-blocks for traceability. | AE12: True. System architecture and simulation implemented. | AF12: TRUE | AG12: The system is implemented and evaluated using real-case scenarios and tools like JMeter. | AH12: True. Novel use of side-blocks and smart contracts for auditing. | AI12: TRUE | AJ12: The paper introduces a novel blockchain-based system (MeDShare) for medical data sharing. | AK12: True. Performance and vulnerability analysis conducted. | AL12: TRUE | AM12: The system is empirically evaluated for latency and performance under simulated loads. | AN12: False. No industrial deployment. | AO12: FALSE | AP12: There is no evidence of evaluation in an actual industrial or production environment. | AQ12: False. Not conceptual only. | AR12: FALSE | AS12: The paper presents a fully implemented system, not just a conceptual framework. | AT12: False. Not based on personal experience. | AU12: FALSE | AV12: The paper is based on technical implementation and evaluation, not solely on author opinion or experience. | AW12: Evaluation research | AX12: Evaluation research | AY12: Simulation as an empirical method | AZ12: Controlled experiment with practitioners | BA12: MeDShare enables secure, trust-less medical data sharing with auditability and access control via smart contracts. | BB12: MeDShare effectively enables secure, trust-less sharing of medical data among cloud service providers. It ensures data provenance, auditing, and access control using blockchain and smart contracts. The system performs comparably to existing solutions while offering enhanced security and traceability. | BC12: MeDShare effectively enables secure, trust-less sharing of medical data among cloud service providers. It ensures data provenance, auditing, and access control using blockchain and smart contracts. The system performs comparably to existing solutions while offering enhanced security and traceability. | BD12: No industrial validation; simulation only. | BE12: The system has increased latency as the number of requests grows, due to the trade-off between security and performance. There is no mention of deployment in real-world industrial settings. | BF12: The system has increased latency as the number of requests grows, due to the trade-off between security and performance. There is no mention of deployment in real-world industrial settings. | BG12: Introduces side-blocks for tracking violations.
A13: 2-s2.0-85045265330 | B13: =VLOOKUP(A13,'Data Set'!A:C,2,FALSE) -> rayyan-218688759 | C13: =VLOOKUP(A13,'Data Set'!A:D,3,FALSE) -> Backward.1 | D13: P012 | E13: 10.1109/PIMRC.2017.8292361 | F13: Integrating Blockchain for Data Sharing and Collaboration in Mobile Healthcare Applications | G13: 2017 | H13: To propose a user-centric blockchain-based system for secure sharing and collaboration of personal health data in mobile healthcare environments. | I13: To propose a user-centric, blockchain-based system for secure and privacy-preserving personal health data sharing and collaboration in mobile healthcare applications. | J13: To propose a user-centric, blockchain-based system for secure and privacy-preserving personal health data sharing and collaboration in mobile healthcare applications. | K13: blockchain, eHealth, data provenance, access control, cloud security | L13: A decentralized permissioned blockchain system using Hyperledger Fabric to collect, validate, and share health data from wearable devices and medical platforms. Data integrity is ensured via Merkle trees and Chainpoint protocol. | M13: The study addresses the healthcare domain, focusing on the challenge of securely sharing personal health data collected via mobile and wearable devices. It proposes a decentralized, permissioned blockchain system built on Hyperledger Fabric to ensure privacy, data integrity, and user ownership. The solution includes a mobile application that collects health data and synchronizes it with a cloud database, while leveraging blockchain channels and membership services for access control and identity management. Comparative analysis with existing systems highlights improvements in scalability, privacy, and interoperability. | N13: The study addresses the healthcare domain, focusing on the challenge of securely sharing personal health data collected via mobile and wearable devices. It proposes a decentralized, permissioned blockchain system built on Hyperledger Fabric to ensure privacy, data integrity, and user ownership. The solution includes a mobile application that collects health data and synchronizes it with a cloud database, while leveraging blockchain channels and membership services for access control and identity management. Comparative analysis with existing systems highlights improvements in scalability, privacy, and interoperability. | O13: Personal health data from wearable and medical devices | P13: Personal health data from wearable devices, medical devices, and manual user input. | Q13: Personal health data from wearable devices, medical devices, and manual user input. | R13: User-centered | S13: user-centered | T13: User-centered | U13: =_xlfn.XLOOKUP(A13,ArticlesArchitecture[[#This Row],[Article ID]],ArticlesArchitecture[[#This Row],[Theme (final decision)]]) -> User-centered | V13: Hyperledger Fabric, Merkle Tree, Chainpoint, mobile app, cloud database | W13: The solution is implemented using Hyperledger Fabric, a permissioned blockchain framework. It employs Fabric’s membership service provider for identity management and access control, and utilizes Fabric channels to isolate data sharing domains. Chaincode is used for transaction execution, and Merkle trees are adopted for scalable data integrity verification. Chainpoint is integrated to generate timestamped proofs and anchor data records to the blockchain. The system includes a mobile application for data collection and synchronization with a cloud database, which interacts with the blockchain network via a Fabric client. | X13: The solution is implemented using Hyperledger Fabric, a permissioned blockchain framework. It employs Fabric’s membership service provider for identity management and access control, and utilizes Fabric channels to isolate data sharing domains. Chaincode is used for transaction execution, and Merkle trees are adopted for scalable data integrity verification. Chainpoint is integrated to generate timestamped proofs and anchor data records to the blockchain. The system includes a mobile application for data collection and synchronization with a cloud database, which interacts with the blockchain network via a Fabric client. | Y13: To ensure privacy, integrity, and traceability of health data shared among users, healthcare providers, and insurers. | Z13: Tracking is necessary to ensure the integrity, privacy, and ownership of personal health data. It enables secure sharing with healthcare providers and insurance companies, supports data provenance, and facilitates auditing and accountability. The tracking mechanism helps detect unauthorized modifications and ensures that all data access and updates are recorded immutably on the blockchain. | AA13: Tracking is necessary to ensure the integrity, privacy, and ownership of personal health data. It enables secure sharing with healthcare providers and insurance companies, supports data provenance, and facilitates auditing and accountability. The tracking mechanism helps detect unauthorized modifications and ensures that all data access and updates are recorded immutably on the blockchain. | AB13: Yes. Malicious entities can be identified via blockchain audit trails and access logs. | AC13: Yes, the system enables identification of the responsible party in case of data leakage. The cloud database stores access records and policies, and all access activities are recorded on the blockchain, making them traceable and accountable. | AD13: Yes, the system enables identification of the responsible party in case of data leakage. The cloud database stores access records and policies, and all access activities are recorded on the blockchain, making them traceable and accountable. | AE13: True. The system is implemented and tested. | AF13: TRUE | AG13: The system is implemented and tested with real data collection and synchronization using mobile and wearable devices. | AH13: True. A novel integration of blockchain and Merkle trees for healthcare. | AI13: TRUE | AJ13: The paper introduces a novel blockchain-based architecture for personal health data sharing using Hyperledger Fabric and Merkle trees. | AK13: True. Performance evaluation and security analysis conducted. | AL13: TRUE | AM13: The paper includes performance evaluation experiments measuring integrity proof generation and validation times. | AN13: False. No industrial deployment. | AO13: FALSE | AP13: There is no evidence of evaluation in an industrial context; the testing appears to be conducted in a controlled environment. | AQ13: False. A concrete system is proposed. | AR13: FALSE | AS13: The paper presents a fully implemented system rather than a conceptual framework. | AT13: False. Not based on personal experience. | AU13: FALSE | AV13: The study is based on system implementation and empirical evaluation, not solely on author opinions or experiences. | AW13: Evaluation research | AX13: Evaluation research | AY13: Simulation as an empirical method | AZ13: Prototyping | BA13: The system achieves scalable, secure, and efficient health data sharing with low latency and strong privacy guarantees. | BB13: The proposed system successfully enables secure, scalable, and privacy-preserving personal health data sharing. It ensures data integrity through Merkle tree-based batching and blockchain anchoring. The system supports fine-grained access control and user-defined privacy policies. Performance evaluation demonstrates low latency and high scalability, validating the system’s efficiency for large datasets. | BC13: The proposed system successfully enables secure, scalable, and privacy-preserving personal health data sharing. It ensures data integrity through Merkle tree-based batching and blockchain anchoring. The system supports fine-grained access control and user-defined privacy policies. Performance evaluation demonstrates low latency and high scalability, validating the system’s efficiency for large datasets. | BD13: No industrial validation; limited to simulation. | BE13: The paper does not discuss deployment in real-world healthcare institutions or long-term usability studies. Industrial validation is not addressed. | BF13: The paper does not discuss deployment in real-world healthcare institutions or long-term usability studies. Industrial validation is not addressed. | BG13: Anchoring Merkle roots to blockchain channels enhances data integrity. | BH13: The article provides a comprehensive implementation and evaluation of a blockchain-based health data sharing system, but lacks industrial deployment evidence.
A14: 2-s2.0-85053453440 | B14: =VLOOKUP(A14,'Data Set'!A:C,2,FALSE) -> rayyan-218688549 | C14: =VLOOKUP(A14,'Data Set'!A:D,3,FALSE) -> Backward.1 | D14: P013 | E14: n/a | F14: Make users own their data: a decentralized personal data store prototype based on Ethereum and IPFS | G14: 2018 | H14: To develop a decentralized personal data store (PDS) allowing users to control access to their data and devices | I14: To propose and validate a decentralized Personal Data Store prototype that empowers users with ownership and control over their personal data and devices, using Ethereum and IPFS technologies. | J14: To propose and validate a decentralized Personal Data Store prototype that empowers users with ownership and control over their personal data and devices, using Ethereum and IPFS technologies. | K14: personal data store, decentralized identity, IPFS, Ethereum, privacy management | L14: DIM (Decentralized Identity Manager) stores user profiles in IPFS and links them via Ethereum smart contracts; users manage access via mobile app | M14: The study addresses the challenge of personal data protection in the context of pervasive digital services. It proposes the Decentralized Identity Manager (DIM), a Personal Data Store based on Ethereum and IPFS, which allows users to manage their personal data and device access without relying on centralized authorities. The solution includes a multidimensional user profile modeled using schema.org ontology, stored in JSON-LD format, and encrypted for privacy. The system enables users to share data selectively with services through smart contracts and QR code-based requests. Comparative analysis includes centralized and decentralized PDSs such as MyDex, IRMA, OpenPDS, Onename, and BITNATION, highlighting the novelty and advantages of DIM in terms of decentralization, privacy, and contextual service personalization. | N14: The study addresses the challenge of personal data protection in the context of pervasive digital services. It proposes the Decentralized Identity Manager (DIM), a Personal Data Store based on Ethereum and IPFS, which allows users to manage their personal data and device access without relying on centralized authorities. The solution includes a multidimensional user profile modeled using schema.org ontology, stored in JSON-LD format, and encrypted for privacy. The system enables users to share data selectively with services through smart contracts and QR code-based requests. Comparative analysis includes centralized and decentralized PDSs such as MyDex, IRMA, OpenPDS, Onename, and BITNATION, highlighting the novelty and advantages of DIM in terms of decentralization, privacy, and contextual service personalization. | O14: Personal data and device metadata | P14: Personal data, device ownership, user actions, locations, and interests extracted from social networks. | Q14: Personal data, device ownership, user actions, locations, and interests extracted from social networks. | R14: User-centered | S14: user-centered | T14: User-centered | U14: =_xlfn.XLOOKUP(A14,ArticlesArchitecture[[#This Row],[Article ID]],ArticlesArchitecture[[#This Row],[Theme (final decision)]]) -> User-centered | V14: Ethereum smart contracts, IPFS, Android app, JSON-LD, schema.org ontology | W14: The solution integrates Ethereum for decentralized identity management and smart contract execution, and IPFS for distributed file storage. User profiles are modeled using schema.org ontology in JSON-LD format. The Android prototype uses IPFSDroid for IPFS integration and Ethereum Lightwallet for blockchain interactions. Encryption is applied at two levels: asymmetric keys for Ethereum and symmetric keys for IPFS. The system includes QR code-based data sharing and interest mining from Facebook and Twitter. | X14: The solution integrates Ethereum for decentralized identity management and smart contract execution, and IPFS for distributed file storage. User profiles are modeled using schema.org ontology in JSON-LD format. The Android prototype uses IPFSDroid for IPFS integration and Ethereum Lightwallet for blockchain interactions. Encryption is applied at two levels: asymmetric keys for Ethereum and symmetric keys for IPFS. The system includes QR code-based data sharing and interest mining from Facebook and Twitter. | Y14: To empower users with control over personal data and device sharing in pervasive services | Z14: Tracking is necessary to enable users to manage and control their personal data and device access in a decentralized manner. It aims to ensure privacy, support contextualized service delivery, and empower users with ownership and selective sharing capabilities. Tracking contributes to solving trust issues in centralized systems and facilitates pervasive service personalization. | AA14: Tracking is necessary to enable users to manage and control their personal data and device access in a decentralized manner. It aims to ensure privacy, support contextualized service delivery, and empower users with ownership and selective sharing capabilities. Tracking contributes to solving trust issues in centralized systems and facilitates pervasive service personalization. | AB14: Yes; Ethereum keys and symmetric encryption used for access control | AC14: Yes, the approach enables identification of the responsible party through smart contracts that log user identity and data sharing actions. The Ethereum address and profile hash stored in the blockchain serve as immutable records of data ownership and sharing. | AD14: Yes, the approach enables identification of the responsible party through smart contracts that log user identity and data sharing actions. The Ethereum address and profile hash stored in the blockchain serve as immutable records of data ownership and sharing. | AE14: True. Android app and Ethereum/IPFS integration implemented | AF14: TRUE | AG14: The prototype was implemented and tested in laboratory settings with real devices and services. | AH14: True. Novel integration of ontology-based profile with blockchain | AI14: TRUE | AJ14: The paper introduces a novel decentralized Personal Data Store using Ethereum and IPFS. | AK14: True. Functional validation with scenarios (hotel booking, chat transfer) | AL14: TRUE | AM14: Structured evaluation scenarios were conducted to validate functionalities such as data insertion, sharing, and interest mining. | AN14: False. No industrial deployment | AO14: FALSE | AP14: The validation was performed in laboratory settings, not in an industrial context. | AQ14: False. Full system implemented | AR14: FALSE | AS14: The paper presents a fully implemented prototype, not just a conceptual framework. | AT14: False. Not based on personal experience | AU14: FALSE | AV14: The study is based on technical implementation and evaluation, not solely on author opinions or experiences. | AW14: Evaluation research | AX14: Evaluation research | AY14: Prototyping | AZ14: Laboratory experiment | BA14: DIM enables decentralized, privacy-preserving data control with device sharing capabilities | BB14: The Decentralized Identity Manager successfully enables users to manage personal data and devices securely and privately. The use of Ethereum and IPFS ensures decentralization and data ownership. The prototype supports explicit and implicit data insertion, selective sharing, and integration with social networks. Future work includes expanding the system beyond the Servify ecosystem and addressing GDPR compatibility. | BC14: The Decentralized Identity Manager successfully enables users to manage personal data and devices securely and privately. The use of Ethereum and IPFS ensures decentralization and data ownership. The prototype supports explicit and implicit data insertion, selective sharing, and integration with social networks. Future work includes expanding the system beyond the Servify ecosystem and addressing GDPR compatibility. | BD14: GDPR compatibility and quantum vulnerability discussed; no industrial validation | BE14: Validation was limited to laboratory settings; real-world deployment and GDPR compliance remain future challenges. | BF14: Validation was limited to laboratory settings; real-world deployment and GDPR compliance remain future challenges. | BG14: Uses schema.org ontology for profile modeling | BH14: The article provides a comprehensive technical implementation and evaluation of a decentralized personal data management system. It includes ontology modeling, encryption strategies, and integration with social platforms.
A15: 2-s2.0-85058311800 | B15: =VLOOKUP(A15,'Data Set'!A:C,2,FALSE) -> rayyan-218688443 | C15: =VLOOKUP(A15,'Data Set'!A:D,3,FALSE) -> Backward.1 | D15: P014 | E15: 10.1109/HealthCom.2018.8531160 | F15: A Blockchain-based Architecture Framework for Secure Sharing of Personal Health Data | G15: 2018 | H15: To design a blockchain-supported health information exchange that enforces acceptable use policies via smart contracts | I15: To propose a blockchain-supported architectural framework that enables secure control and sharing of personal health data in Health Information Exchanges, ensuring data privacy, ownership, and post-transmission control through smart contracts and user-defined policies. | J15: To propose a blockchain-supported architectural framework that enables secure control and sharing of personal health data in Health Information Exchanges, ensuring data privacy, ownership, and post-transmission control through smart contracts and user-defined policies. | K15: health data sharing, smart contracts, data control, blockchain, privacy enforcement | L15: Uses smart contracts to enforce patient-defined data usage policies; monitors connectivity and timing to detect misuse; destroys data upon violation | M15: The study addresses the healthcare domain, specifically the challenge of controlling personal health data after it has been shared within Health Information Exchanges. The proposed solution is a blockchain-based architecture that integrates smart contracts and user-defined acceptable use policies to enforce data control and privacy. The system allows patients to define policies at registration, which are then enforced through smart contracts attached to data transactions. The architecture includes cryptographic key management, a query manager, processing nodes, and a smart contract center. Comparative analysis with existing systems highlights the novelty of incorporating timed smart contracts and continuous monitoring to ensure compliance with data usage policies, offering enhanced security and privacy over traditional systems. | N15: The study addresses the healthcare domain, specifically the challenge of controlling personal health data after it has been shared within Health Information Exchanges. The proposed solution is a blockchain-based architecture that integrates smart contracts and user-defined acceptable use policies to enforce data control and privacy. The system allows patients to define policies at registration, which are then enforced through smart contracts attached to data transactions. The architecture includes cryptographic key management, a query manager, processing nodes, and a smart contract center. Comparative analysis with existing systems highlights the novelty of incorporating timed smart contracts and continuous monitoring to ensure compliance with data usage policies, offering enhanced security and privacy over traditional systems. | O15: Personal health records and access logs | P15: Personal health data and its usage after transmission, including compliance with acceptable use policies. | Q15: Personal health data and its usage after transmission, including compliance with acceptable use policies. | R15: Server-centered | S15: user-centered | T15: User-centered | U15: =_xlfn.XLOOKUP(A15,ArticlesArchitecture[[#This Row],[Article ID]],ArticlesArchitecture[[#This Row],[Theme (final decision)]]) -> User-centered | V15: Ethereum blockchain, Solidity smart contracts, Truffle, web3.js, Ubuntu, Docker | W15: The solution is implemented using the Ethereum blockchain platform, with smart contracts developed in Solidity. The system uses cryptographic primitives including SHA256 hashing and public/private key pairs for authentication and authorization. Truffle is used for contract deployment and management, while Docker and Ubuntu 16.04.1 provide the runtime environment. Web3.js facilitates communication between web clients and the blockchain via RPC calls. JMeter is used for performance testing, and Merkle tree structures are employed to optimize data batching and retrieval. The implementation demonstrates a fully functional prototype rather than a conceptual model. | X15: The solution is implemented using the Ethereum blockchain platform, with smart contracts developed in Solidity. The system uses cryptographic primitives including SHA256 hashing and public/private key pairs for authentication and authorization. Truffle is used for contract deployment and management, while Docker and Ubuntu 16.04.1 provide the runtime environment. Web3.js facilitates communication between web clients and the blockchain via RPC calls. JMeter is used for performance testing, and Merkle tree structures are employed to optimize data batching and retrieval. The implementation demonstrates a fully functional prototype rather than a conceptual model. | Y15: To ensure post-transmission control of health data and enforce patient-defined policies | Z15: Tracking is necessary to ensure that personal health data is used strictly according to the policies defined by the data owner. It aims to prevent unauthorized access and misuse of data after it has been shared, thereby enhancing data privacy, ownership, and compliance with healthcare regulations. The tracking mechanism also supports accountability by enabling monitoring and enforcement through smart contracts. | AA15: Tracking is necessary to ensure that personal health data is used strictly according to the policies defined by the data owner. It aims to prevent unauthorized access and misuse of data after it has been shared, thereby enhancing data privacy, ownership, and compliance with healthcare regulations. The tracking mechanism also supports accountability by enabling monitoring and enforcement through smart contracts. | AB15: Yes; smart contracts monitor and destroy data upon misuse | AC15: Yes, the system enables responsibility attribution through the use of cryptographic keys and blockchain transaction logs. Violations of data usage policies trigger smart contract actions, including data destruction and alerts to the security monitor, which can impose penalties such as blacklisting or legal action. | AD15: Yes, the system enables responsibility attribution through the use of cryptographic keys and blockchain transaction logs. Violations of data usage policies trigger smart contract actions, including data destruction and alerts to the security monitor, which can impose penalties such as blacklisting or legal action. | AE15: True. Implemented on Ethereum and tested with simulated users | AF15: TRUE | AG15: The system was implemented and tested using Ethereum, Docker, and JMeter in a simulated environment with up to 100,000 users. | AH15: True. Novel use of smart contracts for post-access control | AI15: TRUE | AJ15: The paper introduces a novel blockchain-based framework with timed smart contracts for post-transmission data control. | AK15: True. Performance evaluation with JMeter and Truffle | AL15: TRUE | AM15: The authors conducted experimental evaluations including performance metrics such as latency and response time. | AN15: False. No industrial deployment | AO15: FALSE | AP15: There is no evidence that the system was evaluated in an actual industrial or clinical setting. | AQ15: False. Full system implemented | AR15: FALSE | AS15: The paper presents a fully implemented system, not just a conceptual framework. | AT15: False. Not based on personal experience | AU15: FALSE | AV15: The paper is based on technical implementation and evaluation, not solely on author opinions or experiences. | AW15: Evaluation research | AX15: Evaluation research | AY15: Prototyping | AZ15: Controlled experiment with practitioners | BA15: The system enables secure, policy-driven sharing of health data with post-access control and low latency | BB15: The proposed blockchain-based framework effectively enforces data usage policies through smart contracts, ensuring secure and private sharing of personal health data. The system demonstrates low latency and high scalability, making it suitable for large-scale health information exchanges. Comparative analysis shows that the framework offers superior access control and privacy preservation compared to existing solutions. | BC15: The proposed blockchain-based framework effectively enforces data usage policies through smart contracts, ensuring secure and private sharing of personal health data. The system demonstrates low latency and high scalability, making it suitable for large-scale health information exchanges. Comparative analysis shows that the framework offers superior access control and privacy preservation compared to existing solutions. | BD15: Scalability and industrial adoption not tested; limited to Ethereum prototype | BE15: The paper does not discuss integration with real-world healthcare systems or address scalability in production environments. The method for combining data with smart contracts in replies is also not detailed. | BF15: The paper does not discuss integration with real-world healthcare systems or address scalability in production environments. The method for combining data with smart contracts in replies is also not detailed. | BG15: Uses connectivity monitoring to detect unauthorized access
A16: 2-s2.0-85067254500 | B16: =VLOOKUP(A16,'Data Set'!A:C,2,FALSE) -> rayyan-218688565 | C16: =VLOOKUP(A16,'Data Set'!A:D,3,FALSE) -> Backward.1 | D16: P015 | E16: 10.1109/Cybermatics_2018.2018.00253 | F16: Blockchain-Based, Decentralized Access Control for IPFS | G16: 2018 | H16: To design and implement a decentralized access control mechanism for IPFS using Ethereum smart contracts, enabling secure and selective file sharing. | I16: To design and implement a decentralized access control mechanism for the InterPlanetary File System (IPFS) using Ethereum smart contracts, enabling secure and selective sharing of large files containing sensitive information. | J16: To design and implement a decentralized access control mechanism for the InterPlanetary File System (IPFS) using Ethereum smart contracts, enabling secure and selective sharing of large files containing sensitive information. | K16: blockchain, access control, IPFS, smart contracts, data privacy, decentralized systems | L16: The study proposes acl-IPFS, a modified version of IPFS integrated with Ethereum smart contracts. The system tracks file access permissions using cryptographic hashes and enforces access control via smart contracts. It allows users to register files, grant/revoke access, and verify permissions through Ethereum-linked identities. | M16: The study addresses the inefficiency of storing large files directly on blockchains due to replication and cost constraints. It proposes a modified version of IPFS, named acl-IPFS, which integrates Ethereum smart contracts to manage access control lists. The smart contract records ownership and permissions, while the acl-IPFS software enforces these permissions during file operations. This hybrid system allows users to register files, grant or revoke access, and verify permissions using cryptographic hashes. Comparative analysis with standard IPFS demonstrates that while acl-IPFS introduces latency due to blockchain interactions, it remains viable for sensitive data sharing, particularly in regulated domains such as finance. | N16: The study addresses the inefficiency of storing large files directly on blockchains due to replication and cost constraints. It proposes a modified version of IPFS, named acl-IPFS, which integrates Ethereum smart contracts to manage access control lists. The smart contract records ownership and permissions, while the acl-IPFS software enforces these permissions during file operations. This hybrid system allows users to register files, grant or revoke access, and verify permissions using cryptographic hashes. Comparative analysis with standard IPFS demonstrates that while acl-IPFS introduces latency due to blockchain interactions, it remains viable for sensitive data sharing, particularly in regulated domains such as finance. | O16: Files stored in IPFS (identified by chunk hashes) and their access permissions (grants/revocations) on Ethereum. | P16: Cryptographic hashes of file chunks stored in IPFS | Q16: Cryptographic hashes of file chunks stored in IPFS | R16: Server-centered | S16: hybrid | T16: Server-centered | U16: =_xlfn.XLOOKUP(A16,ArticlesArchitecture[[#This Row],[Article ID]],ArticlesArchitecture[[#This Row],[Theme (final decision)]]) -> Hybrid (user-centered and server-centered) | V16: Ethereum blockchain, Solidity smart contracts, IPFS (modified), Golang (permissions package), Docker (experimental setup). The solution is fully implemented and tested. | W16: The solution is implemented using Golang, leveraging existing Go implementations of Ethereum and IPFS. Ethereum smart contracts are written in Solidity and compiled with version 0.4.20. The permissions package interacts with the smart contract via go-ethereum’s abigen tool, enabling transaction management and verification. The acl-IPFS nodes use modified IPFS software to enforce access control, while Ethereum nodes execute the smart contract. The architecture supports concurrent transaction tracking and memory management through Go routines, ensuring scalability and modularity. | X16: The solution is implemented using Golang, leveraging existing Go implementations of Ethereum and IPFS. Ethereum smart contracts are written in Solidity and compiled with version 0.4.20. The permissions package interacts with the smart contract via go-ethereum’s abigen tool, enabling transaction management and verification. The acl-IPFS nodes use modified IPFS software to enforce access control, while Ethereum nodes execute the smart contract. The architecture supports concurrent transaction tracking and memory management through Go routines, ensuring scalability and modularity. | Y16: To ensure that sensitive files stored off-chain in IPFS are only accessible to authorized entities, enabling compliance with privacy regulations such as GDPR and AMLD. | Z16: Tracking is necessary to enforce access control over sensitive data stored in IPFS. It ensures that only authorized users can access specific file chunks, thereby supporting compliance with privacy regulations such as GDPR. The tracking mechanism links file hashes to ownership and permissions, enabling secure data sharing and preventing unauthorized access. | AA16: Tracking is necessary to enforce access control over sensitive data stored in IPFS. It ensures that only authorized users can access specific file chunks, thereby supporting compliance with privacy regulations such as GDPR. The tracking mechanism links file hashes to ownership and permissions, enabling secure data sharing and preventing unauthorized access. | AB16: Yes. Each node is linked to an Ethereum account, and access requests are signed with the public key, allowing verification and accountability. | AC16: Yes, the approach enables identification of responsible parties through Ethereum account linkage. Each acl-IPFS node signs requests using its Ethereum account, allowing verification of identity and accountability in case of data leakage. | AD16: Yes, the approach enables identification of responsible parties through Ethereum account linkage. Each acl-IPFS node signs requests using its Ethereum account, allowing verification of identity and accountability in case of data leakage. | AE16: False. The solution was tested in an experimental setup but not deployed in a real-world industrial context. | AF16: TRUE | AG16: The system is implemented and tested using Docker containers with Ethereum and IPFS nodes, demonstrating practical application. | AH16: True. The paper introduces a novel integration of access control into IPFS using Ethereum smart contracts. | AI16: TRUE | AJ16: The paper introduces a novel integration of Ethereum smart contracts with IPFS to enforce decentralized access control. | AK16: True. The study includes latency and stress tests conducted in a controlled environment using Docker containers. | AL16: TRUE | AM16: Empirical evaluation is conducted through latency and stress tests comparing acl-IPFS with standard IPFS. | AN16: False. No industrial or organizational validation was performed. | AO16: FALSE | AP16: The solution is not evaluated in an industrial context but rather in a controlled experimental setup. | AQ16: False. The paper presents a practical implementation, not just a conceptual framework. | AR16: FALSE | AS16: The paper presents a fully implemented system, not just a conceptual framework. | AT16: False. The paper is based on experimental results, not solely on author opinion or experience. | AU16: FALSE | AV16: The study is based on technical implementation and experimentation, not solely on author experience. | AW16: Validation research | AX16: Evaluation research | AY16: Laboratory experiment (machine or human) | AZ16: Prototyping | BA16: The acl-IPFS system successfully enforces decentralized access control for IPFS files using Ethereum smart contracts. It introduces minimal latency and supports scalable operations. The approach enables secure file sharing and compliance with privacy regulations. | BB16: Acl-IPFS successfully integrates access control into IPFS using Ethereum smart contracts. The system allows secure file sharing with permission enforcement. Experimental results show that while acl-IPFS introduces latency due to blockchain interactions, it remains effective for sensitive data sharing. The architecture supports scalability and compliance with privacy regulations. | BC16: Acl-IPFS successfully integrates access control into IPFS using Ethereum smart contracts. The system allows secure file sharing with permission enforcement. Experimental results show that while acl-IPFS introduces latency due to blockchain interactions, it remains effective for sensitive data sharing. The architecture supports scalability and compliance with privacy regulations. | BD16: The system was evaluated only in a simulated environment. Real-world deployment and user behavior were not assessed. Collaborative agreements among node operators are assumed but not implemented. | BE16: The system assumes collaborative agreements among node operators to prevent unauthorized sharing outside the acl-IPFS network. It does not address enforcement beyond technical controls. | BF16: The system assumes collaborative agreements among node operators to prevent unauthorized sharing outside the acl-IPFS network. It does not address enforcement beyond technical controls. | BG16: The paper presents a use case for KYC compliance in financial institutions, highlighting the relevance of decentralized access control for regulatory adherence. | BH16: The article provides a detailed implementation and evaluation of a decentralized access control system for IPFS, suitable for privacy-sensitive applications.
A17: 2-s2.0-85060327879 | B17: =VLOOKUP(A17,'Data Set'!A:C,2,FALSE) -> rayyan-218688278 | C17: =VLOOKUP(A17,'Data Set'!A:D,3,FALSE) -> Backward.1 | D17: P016 | E17: 10.1016/j.future.2019.01.018 | F17: Blockchain based searchable encryption for electronic health record sharing | G17: 2019 | H17: To propose a blockchain-based searchable encryption scheme for secure EHR sharing | I17: To propose a blockchain-based searchable encryption scheme that enables secure and efficient sharing of electronic health records (EHRs) among healthcare institutions and individuals, while ensuring data integrity, confidentiality, and fairness. | J17: To propose a blockchain-based searchable encryption scheme that enables secure and efficient sharing of electronic health records (EHRs) among healthcare institutions and individuals, while ensuring data integrity, confidentiality, and fairness. | K17: blockchain, searchable encryption, smart contracts, privacy-preserving search | L17: Indexing EHRs via complex Boolean expressions; smart contracts for search; AES and PRE for encryption; Ethereum-based implementation | M17: The study addresses the challenge of securely sharing electronic health records (EHRs) across different healthcare institutions and individuals. The proposed solution introduces a blockchain-based searchable encryption scheme that allows data owners to construct complex Boolean indices for EHRs and store them on the blockchain. This enables users to perform secure searches without revealing sensitive data. The actual EHRs are encrypted and stored in a public cloud, while the blockchain ensures integrity, anti-tampering, and traceability of the index. Smart contracts are employed to facilitate fair transactions and monetary rewards, ensuring that honest participants are compensated and malicious actors are penalized. Comparative analysis highlights the scheme’s superiority over existing single-keyword search approaches by supporting complex queries and decentralized control. | N17: The study addresses the challenge of securely sharing electronic health records (EHRs) across different healthcare institutions and individuals. The proposed solution introduces a blockchain-based searchable encryption scheme that allows data owners to construct complex Boolean indices for EHRs and store them on the blockchain. This enables users to perform secure searches without revealing sensitive data. The actual EHRs are encrypted and stored in a public cloud, while the blockchain ensures integrity, anti-tampering, and traceability of the index. Smart contracts are employed to facilitate fair transactions and monetary rewards, ensuring that honest participants are compensated and malicious actors are penalized. Comparative analysis highlights the scheme’s superiority over existing single-keyword search approaches by supporting complex queries and decentralized control. | O17: EHR indexes and encrypted records | P17: Identifiers of encrypted electronic health records (EHRs) based on complex Boolean expressions. | Q17: Identifiers of encrypted electronic health records (EHRs) based on complex Boolean expressions. | R17: Server-centered | S17: hybrid | T17: Server-centered | U17: =_xlfn.XLOOKUP(A17,ArticlesArchitecture[[#This Row],[Article ID]],ArticlesArchitecture[[#This Row],[Theme (final decision)]]) -> Server-centered | V17: Ethereum, AES, Proxy Re-encryption, MongoDB, Python, Solidity | W17: The proposed solution integrates blockchain technology, specifically Ethereum smart contracts, with searchable symmetric encryption and decentralized storage systems like the InterPlanetary File System (IPFS). The system comprises five core algorithms: Setup, BuildIndex, Enc, Trapdoor, and Search. MongoDB is used to store plaintext EHRs, which are then encrypted using symmetric key cryptography. The index, constructed from complex Boolean expressions, is stored on the blockchain via smart contracts. These contracts manage search operations and monetary rewards. The implementation is conceptual, with performance evaluations conducted using simulated datasets and environments. | X17: The proposed solution integrates blockchain technology, specifically Ethereum smart contracts, with searchable symmetric encryption and decentralized storage systems like the InterPlanetary File System (IPFS). The system comprises five core algorithms: Setup, BuildIndex, Enc, Trapdoor, and Search. MongoDB is used to store plaintext EHRs, which are then encrypted using symmetric key cryptography. The index, constructed from complex Boolean expressions, is stored on the blockchain via smart contracts. These contracts manage search operations and monetary rewards. The implementation is conceptual, with performance evaluations conducted using simulated datasets and environments. | Y17: To enable secure, verifiable search over encrypted EHRs with fairness and soundness | Z17: Tracking is necessary to enable secure and fair access to encrypted EHRs stored in decentralized systems. It ensures that users can retrieve accurate search results without compromising patient privacy. The tracking mechanism supports auditability, integrity verification, and financial fairness through smart contracts, thereby addressing issues of trust and accountability in data sharing. | AA17: Tracking is necessary to enable secure and fair access to encrypted EHRs stored in decentralized systems. It ensures that users can retrieve accurate search results without compromising patient privacy. The tracking mechanism supports auditability, integrity verification, and financial fairness through smart contracts, thereby addressing issues of trust and accountability in data sharing. | AB17: Yes; via smart contracts and incentive mechanisms | AC17: Yes, the approach enables identification of responsible parties through the use of smart contracts and blockchain traceability. Malicious activities, such as incorrect search results or unauthorized access, can be detected and attributed to specific entities, ensuring accountability. | AD17: Yes, the approach enables identification of responsible parties through the use of smart contracts and blockchain traceability. Malicious activities, such as incorrect search results or unauthorized access, can be detected and attributed to specific entities, ensuring accountability. | AE17: False – No real-world deployment | AF17: FALSE | AG17: The scheme is evaluated using simulated datasets and environments, not deployed in a real-world setting. | AH17: True – Novel searchable encryption with fairness | AI17: TRUE | AJ17: The paper introduces a novel blockchain-based searchable encryption scheme tailored for EHR sharing, supporting complex Boolean queries. | AK17: True – Performance evaluation on Ethereum testnets | AL17: TRUE | AM17: Structured performance evaluations are conducted using simulated datasets and environments. | AN17: False – No industrial validation | AO17: FALSE | AP17: There is no evidence of evaluation in an industrial or production healthcare environment. | AQ17: False – Not conceptual only | AR17: FALSE | AS17: The paper presents a detailed construction and performance evaluation, not just a conceptual framework. | AT17: False – Not based on author opinion | AU17: FALSE | AV17: The study is based on technical implementation and evaluation, not solely on author experience or opinion. | AW17: Validation research | AX17: Validation research | AY17: Simulation as an empirical method | AZ17: Simulation | BA17: Scheme supports secure, fair, and verifiable search over encrypted EHRs using smart contracts | BB17: The proposed blockchain-based searchable encryption scheme for EHR sharing supports complex Boolean and range queries, ensuring fairness, soundness, and confidentiality. It outperforms existing single-keyword search schemes in terms of functionality and robustness. Performance evaluations demonstrate the efficiency of index construction and search operations, with most overhead incurred during smart contract execution. The scheme is feasible and effective for secure EHR sharing in decentralized environments. | BC17: The proposed blockchain-based searchable encryption scheme for EHR sharing supports complex Boolean and range queries, ensuring fairness, soundness, and confidentiality. It outperforms existing single-keyword search schemes in terms of functionality and robustness. Performance evaluations demonstrate the efficiency of index construction and search operations, with most overhead incurred during smart contract execution. The scheme is feasible and effective for secure EHR sharing in decentralized environments. | BD17: No real-world deployment; limited to simulation | BE17: The scheme has not been tested in a real-world healthcare setting due to the lack of access to publicly available EHR databases or collaboration with hospitals. The evaluation relies on simulated datasets, which may not fully represent practical deployment scenarios. | BF17: The scheme has not been tested in a real-world healthcare setting due to the lack of access to publicly available EHR databases or collaboration with hospitals. The evaluation relies on simulated datasets, which may not fully represent practical deployment scenarios. | BG17: Strong focus on fairness and incentive mechanisms | BH17: The article provides a comprehensive technical framework and simulation-based evaluation but lacks real-world deployment or industrial validation.
A18: 2-s2.0-85064977458 | B18: =VLOOKUP(A18,'Data Set'!A:C,2,FALSE) -> rayyan-218688371 | C18: =VLOOKUP(A18,'Data Set'!A:D,3,FALSE) -> Backward.1 | D18: P017 | E18: 10.1109/ICCNC.2019.8685552 | F18: Security and Privacy of Electronic Health Records: Decentralized and Hierarchical Data Sharing using Smart Contracts | G18: 2019 | H18: To propose a decentralized scheme for secure EHR sharing using smart contracts and hierarchical access control | I18: To propose a secure, private, and efficient electronic health record sharing and management scheme that empowers patients with control over their medical data using blockchain and smart contracts. | J18: To propose a secure, private, and efficient electronic health record sharing and management scheme that empowers patients with control over their medical data using blockchain and smart contracts. | K18: blockchain, smart contracts, CP-ABE, hierarchical access, healthcare privacy | L18: Smart contracts on Ethereum for access control; CP-ABE and privilege-based multilevel sharing; symmetric encryption of EHR segments | M18: The study addresses the healthcare domain, focusing on the problem of insecure, inefficient, and centralized electronic health record systems that compromise patient privacy and data interoperability. The proposed solution introduces a decentralized data sharing scheme leveraging blockchain and smart contracts, enabling patients to control access to their records based on fine-grained privacy preferences. The system incorporates Ciphertext Policy Attribute-Based Encryption and a privilege-based multilevel organizational data-sharing model to enforce hierarchical access control. Comparative analysis highlights improvements over traditional centralized systems in terms of security, privacy, and efficiency. | N18: The study addresses the healthcare domain, focusing on the problem of insecure, inefficient, and centralized electronic health record systems that compromise patient privacy and data interoperability. The proposed solution introduces a decentralized data sharing scheme leveraging blockchain and smart contracts, enabling patients to control access to their records based on fine-grained privacy preferences. The system incorporates Ciphertext Policy Attribute-Based Encryption and a privilege-based multilevel organizational data-sharing model to enforce hierarchical access control. Comparative analysis highlights improvements over traditional centralized systems in terms of security, privacy, and efficiency. | O18: Segmented EHRs based on sensitivity levels | P18: Health data and access permissions to electronic health records. | Q18: Health data and access permissions to electronic health records. | R18: Server-centered | S18: hybrid | T18: Server-centered | U18: =_xlfn.XLOOKUP(A18,ArticlesArchitecture[[#This Row],[Article ID]],ArticlesArchitecture[[#This Row],[Theme (final decision)]]) -> Hybrid (user-centered and server-centered) | V18: Ethereum, CP-ABE, AES, Hash functions, Digital Signatures | W18: The proposed solution integrates blockchain technology, specifically Ethereum smart contracts, with Ciphertext Policy Attribute-Based Encryption (CP-ABE) and a privilege-based multilevel organizational data-sharing scheme (P-MOD). Smart contracts are used for staff registration and access verification, while CP-ABE enables fine-grained access control. Symmetric encryption (e.g., AES) secures record segments, and asymmetric encryption ensures secure key distribution. The system is implemented over the Ethereum public testnet, demonstrating a functional prototype rather than a purely conceptual model. | X18: The proposed solution integrates blockchain technology, specifically Ethereum smart contracts, with Ciphertext Policy Attribute-Based Encryption (CP-ABE) and a privilege-based multilevel organizational data-sharing scheme (P-MOD). Smart contracts are used for staff registration and access verification, while CP-ABE enables fine-grained access control. Symmetric encryption (e.g., AES) secures record segments, and asymmetric encryption ensures secure key distribution. The system is implemented over the Ethereum public testnet, demonstrating a functional prototype rather than a purely conceptual model. | Y18: To allow fine-grained, patient-defined access to EHRs with traceability and collusion resistance | Z18: Tracking is necessary to ensure secure and privacy-preserving access to patient health records. It aims to empower patients with control over their data, allowing selective sharing based on privacy preferences. Tracking access patterns also enables patients to monitor how and when their records are accessed, facilitating revocation and redefinition of access rights when necessary. | AA18: Tracking is necessary to ensure secure and privacy-preserving access to patient health records. It aims to empower patients with control over their data, allowing selective sharing based on privacy preferences. Tracking access patterns also enables patients to monitor how and when their records are accessed, facilitating revocation and redefinition of access rights when necessary. | AB18: Yes; via smart contracts and key-issuer verification | AC18: Yes, the approach enables responsibility attribution by allowing patients to track access history and monitor permission announcements on the blockchain. This transparency helps identify unauthorized access and enables patients to revoke or reassign access rights. | AD18: Yes, the approach enables responsibility attribution by allowing patients to track access history and monitor permission announcements on the blockchain. This transparency helps identify unauthorized access and enables patients to revoke or reassign access rights. | AE18: False – No real-world deployment | AF18: TRUE | AG18: The scheme is implemented using Ethereum smart contracts and tested in a blockchain environment, indicating real-world applicability. | AH18: True – Novel hierarchical access model | AI18: TRUE | AJ18: The paper introduces a novel decentralized data sharing scheme combining smart contracts with hierarchical access control. | AK18: True – Security and performance analysis | AL18: FALSE | AM18: While the paper discusses performance and security, it does not present structured empirical data collection or analysis. | AN18: False – No industrial validation | AO18: FALSE | AP18: There is no evidence of evaluation within an industrial or clinical setting. | AQ18: False – Not conceptual only | AR18: FALSE | AS18: The paper presents an implemented model rather than a purely conceptual framework. | AT18: False – Not based on author opinion | AU18: FALSE | AV18: The study is not based solely on author experience or opinion but includes a technical implementation. | AW18: Validation research | AX18: Solution proposal | AY18: Simulation as an empirical method | AZ18: - | BA18: Scheme enables secure, fine-grained EHR sharing with traceability and collusion resistance | BB18: The proposed scheme successfully empowers patients to control access to their health records, enhances privacy, and eliminates reliance on record-generating institutions. It demonstrates resistance to replay and collusion attacks and supports decentralized access control using smart contracts. The system allows patients to monitor access and revoke permissions, aligning with privacy regulations such as HIPAA. | BC18: The proposed scheme successfully empowers patients to control access to their health records, enhances privacy, and eliminates reliance on record-generating institutions. It demonstrates resistance to replay and collusion attacks and supports decentralized access control using smart contracts. The system allows patients to monitor access and revoke permissions, aligning with privacy regulations such as HIPAA. | BD18: No feasibility study; future work proposed | BE18: The authors acknowledge that the scheme does not guarantee privacy for staff members, as their attributes and access patterns are publicly stored on the blockchain. Additionally, a formal feasibility study is planned for future work. | BF18: The authors acknowledge that the scheme does not guarantee privacy for staff members, as their attributes and access patterns are publicly stored on the blockchain. Additionally, a formal feasibility study is planned for future work. | BG18: Strong emphasis on patient-defined access and HIPAA compliance | BH18: The article presents a technically detailed and implemented solution but lacks empirical evaluation or industrial validation.
A19: 2-s2.0-85068449378 | B19: =VLOOKUP(A19,'Data Set'!A:C,2,FALSE) -> rayyan-172028771 | C19: =VLOOKUP(A19,'Data Set'!A:D,3,FALSE) -> 0 | D19: P018 | E19: 10.24138/jcomss.v15i2.617 | F19: Layer-based Privacy and Security Architecture for Cloud Data Sharing | G19: 2019 | H19: To propose a layered architecture for cloud data sharing that balances data utility and security by categorizing data based on sensitivity and applying appropriate security mechanisms at each layer. | I19: The primary aim of the study is to propose a layered architecture for preserving data privacy and security in cloud environments, particularly when data is shared among multiple entities. | J19: The primary aim of the study is to propose a layered architecture for preserving data privacy and security in cloud environments, particularly when data is shared among multiple entities. | K19: cloud security, data leakage detection, privacy preservation, watermarking, cryptography | L19: The article proposes a layer-based architecture that categorizes data into four sensitivity levels (Public, Confidential, Secret, Top Secret). Each layer applies a different combination of security techniques (e.g., login authentication, AES encryption, watermarking, SHA-3 hashing) to ensure privacy and detect data leakage. Tracking is achieved via watermarking and authentication mechanisms embedded in sensitive documents. | M19: The study addresses the challenge of balancing data utility and security in cloud computing, where data shared among various entities is vulnerable to leakage and misuse. The authors propose a layer-based privacy and security architecture that categorizes data into four sensitivity levels—public, confidential, secret, and top secret—and applies progressively stronger security mechanisms at each level. Techniques such as cryptography, watermarking, and hashing are integrated to ensure confidentiality and enable detection of malicious entities responsible for data leakage. Comparative analysis with existing methods demonstrates the practicality and efficiency of the proposed approach through experimental evaluation. | N19: The study addresses the challenge of balancing data utility and security in cloud computing, where data shared among various entities is vulnerable to leakage and misuse. The authors propose a layer-based privacy and security architecture that categorizes data into four sensitivity levels—public, confidential, secret, and top secret—and applies progressively stronger security mechanisms at each level. Techniques such as cryptography, watermarking, and hashing are integrated to ensure confidentiality and enable detection of malicious entities responsible for data leakage. Comparative analysis with existing methods demonstrates the practicality and efficiency of the proposed approach through experimental evaluation. | O19: Sensitive documents and client identifiers embedded via watermarking and encryption | P19: Sensitive data documents categorized by sensitivity levels | Q19: Sensitive data documents categorized by sensitivity levels | R19: Server-centered | S19: hybrid | T19: Server-centered | U19: =_xlfn.XLOOKUP(A19,ArticlesArchitecture[[#This Row],[Article ID]],ArticlesArchitecture[[#This Row],[Theme (final decision)]]) -> Server-centered | V19: AES-256 and AES-128 encryption, RSA encryption, SHA-3 hashing, digital watermarking (DWT, SVD, DCT), ASP.NET, C#, SQL Server 2014, Visual Studio 2015. The solution is implemented and evaluated experimentally. | W19: The proposed solution integrates multiple technologies including AES-256 and AES-128 for encryption, RSA for key management, SHA-3 for message authentication, and digital watermarking techniques based on DWT, SVD, and DCT. The architecture is implemented in ASP.NET using C# and SQL Server 2014 on Visual Studio 2015. The system operates in a distributed cloud environment with client-server configuration, enabling layered security mechanisms tailored to data sensitivity. The implementation includes modules for client ID generation, watermark embedding and extraction, and authentication verification. | X19: The proposed solution integrates multiple technologies including AES-256 and AES-128 for encryption, RSA for key management, SHA-3 for message authentication, and digital watermarking techniques based on DWT, SVD, and DCT. The architecture is implemented in ASP.NET using C# and SQL Server 2014 on Visual Studio 2015. The system operates in a distributed cloud environment with client-server configuration, enabling layered security mechanisms tailored to data sensitivity. The implementation includes modules for client ID generation, watermark embedding and extraction, and authentication verification. | Y19: To identify the malicious entity responsible for data leakage and verify the leaker using embedded watermark and authentication codes. | Z19: Tracking is necessary to identify and verify malicious entities responsible for data leakage, especially for highly sensitive data. It aims to preserve data confidentiality, ensure accountability, and maintain data utility while minimizing computational overhead. The tracking mechanisms support forensic investigation and secure data sharing by embedding unique identifiers and authentication codes within documents. | AA19: Tracking is necessary to identify and verify malicious entities responsible for data leakage, especially for highly sensitive data. It aims to preserve data confidentiality, ensure accountability, and maintain data utility while minimizing computational overhead. The tracking mechanisms support forensic investigation and secure data sharing by embedding unique identifiers and authentication codes within documents. | AB19: Yes. The model embeds client identifiers and hash codes into documents using watermarking and cryptographic techniques, enabling detection and verification of the guilty client in case of data leakage. | AC19: Yes, the approach enables identification of the responsible party in case of data leakage. For secret and top secret data, watermarking and authentication techniques are used to embed client-specific information, which can be extracted and verified to identify the guilty client. | AD19: Yes, the approach enables identification of the responsible party in case of data leakage. For secret and top secret data, watermarking and authentication techniques are used to embed client-specific information, which can be extracted and verified to identify the guilty client. | AE19: True. Justification: The proposed architecture is implemented and tested using real datasets and cloud servers, demonstrating its practicality. | AF19: TRUE | AG19: The proposed architecture is implemented and evaluated in a real-world cloud environment using actual datasets and servers. | AH19: True. Justification: The paper introduces a novel layered security architecture combining multiple techniques tailored to data sensitivity levels. | AI19: TRUE | AJ19: The paper introduces a novel layered architecture combining multiple security techniques tailored to data sensitivity levels. | AK19: True. Justification: The solution is evaluated experimentally with performance metrics (e.g., processing time across layers and document sizes). | AL19: TRUE | AM19: Structured experimental evaluation is conducted, including performance analysis across different data sizes, user counts, and server configurations. | AN19: False. Justification: The evaluation is conducted in a controlled academic setting, not in an industrial or organizational context. | AO19: FALSE | AP19: There is no evidence of industrial validation or deployment in a commercial setting. | AQ19: False. Justification: The paper goes beyond conceptual discussion and includes implementation and empirical evaluation. | AR19: FALSE | AS19: The paper presents a fully implemented system rather than a conceptual framework. | AT19: False. Justification: The paper is based on experimental results and not solely on author opinion or experience. | AU19: FALSE | AV19: The study is based on empirical evaluation rather than solely on author experience or opinion. | AW19: Evaluation research | AX19: Evaluation research | AY19: Controlled experiment with practitioners | AZ19: Prototyping | BA19: The proposed layered architecture effectively balances data utility and security. It reduces computational overhead by applying appropriate security mechanisms based on data sensitivity. The system successfully identifies and verifies malicious clients responsible for data leakage. | BB19: The proposed layered architecture effectively balances data utility and security by applying appropriate security mechanisms based on data sensitivity. It enables detection and verification of malicious entities responsible for data leakage. Experimental results demonstrate reduced computational overhead and improved processing efficiency when data is shared among multiple users and distributed across cloud servers. | BC19: The proposed layered architecture effectively balances data utility and security by applying appropriate security mechanisms based on data sensitivity. It enables detection and verification of malicious entities responsible for data leakage. Experimental results demonstrate reduced computational overhead and improved processing efficiency when data is shared among multiple users and distributed across cloud servers. | BD19: The evaluation is limited to academic settings and specific data types (e.g., medical datasets). Real-world leakage scenarios and broader data types are suggested for future work. | BE19: The study does not address real-world leakage scenarios or cases where security protocols are violated by trusted entities. Future work is suggested to explore these aspects. | BF19: The study does not address real-world leakage scenarios or cases where security protocols are violated by trusted entities. Future work is suggested to explore these aspects. | BG19: The architecture supports any data type for which watermarking schemes exist. The system includes one-time password mechanisms and tracks client access via IP and embedded identifiers. | BH19: The article provides a comprehensive implementation and evaluation of a layered security architecture for cloud data sharing. It includes detailed algorithms, performance benchmarks, and a comparison with existing methods.
A20: 2-s2.0-85071743770 | B20: =VLOOKUP(A20,'Data Set'!A:C,2,FALSE) -> rayyan-218688262 | C20: =VLOOKUP(A20,'Data Set'!A:D,3,FALSE) -> Backward.1 | D20: P019 | E20: 10.2196/13592 | F20: A Blockchain Framework for Patient-Centered Health Records and Exchange (HealthChain): Evaluation and Proof-of-Concept Study | G20: 2019 | H20: To propose HealthChain, a patient-centered blockchain framework for secure, interoperable health data exchange | I20: To propose and evaluate HealthChain, a patient-centered blockchain framework designed to enhance patient engagement, secure data exchange, and interoperability in healthcare information systems. | J20: To propose and evaluate HealthChain, a patient-centered blockchain framework designed to enhance patient engagement, secure data exchange, and interoperability in healthcare information systems. | K20: blockchain, patient-centered care, smart contracts, proxy re-encryption, redactable blockchain | L20: Mixed-block blockchain with immutable log blocks and redactable patient blocks; smart contracts for access control; proxy re-encryption for secure sharing | M20: The study introduces HealthChain, a blockchain-based framework within the healthcare domain aimed at addressing challenges in patient data access, security, and interoperability. The problem identified is the fragmentation and limited accessibility of electronic health records, which impedes coordinated care and patient agency. HealthChain proposes a mixed-block blockchain architecture with immutable log blocks and redactable patient blocks, leveraging smart contracts and proxy re-encryption to facilitate secure and revocable data sharing. The solution integrates HL7 FHIR standards for interoperability and cryptographic identities for secure transactions. A proof-of-concept implementation was developed and evaluated across 16 configurations, comparing performance metrics such as transmission size, latency, and processing time to identify optimal configurations balancing speed and security. | N20: The study introduces HealthChain, a blockchain-based framework within the healthcare domain aimed at addressing challenges in patient data access, security, and interoperability. The problem identified is the fragmentation and limited accessibility of electronic health records, which impedes coordinated care and patient agency. HealthChain proposes a mixed-block blockchain architecture with immutable log blocks and redactable patient blocks, leveraging smart contracts and proxy re-encryption to facilitate secure and revocable data sharing. The solution integrates HL7 FHIR standards for interoperability and cryptographic identities for secure transactions. A proof-of-concept implementation was developed and evaluated across 16 configurations, comparing performance metrics such as transmission size, latency, and processing time to identify optimal configurations balancing speed and security. | O20: Patient health records (EHRs), metadata, access logs | P20: Patient-generated and accumulated health data formatted as HL7 FHIR messages. | Q20: Patient-generated and accumulated health data formatted as HL7 FHIR messages. | R20: User-centered | S20: user-centered | T20: User-centered | U20: =_xlfn.XLOOKUP(A20,ArticlesArchitecture[[#This Row],[Article ID]],ArticlesArchitecture[[#This Row],[Theme (final decision)]]) -> User-centered | V20: HL7 FHIR, AES, ECC, Proxy Re-encryption, Chameleon Hashing, Java, JSP, HAPI FHIR | W20: The developed solution is implemented as a proof-of-concept using Java 8 and JSP, incorporating two systems: HealthChainServer and HealthChainWebClient. HealthChainServer manages blockchain operations, patient identity validation, and smart contract execution. HealthChainWebClient provides a web interface for patients to manage records and contracts. The system uses HAPI FHIR for document formatting, PCCH for chameleon hashing, and AFGH for proxy re-encryption, built on the Java Pairing-Based Cryptography (jPBC) library. The implementation supports redactable blocks and secure data exchange via smart contracts, with future integration planned into platforms like Hyperledger Fabric. | X20: The developed solution is implemented as a proof-of-concept using Java 8 and JSP, incorporating two systems: HealthChainServer and HealthChainWebClient. HealthChainServer manages blockchain operations, patient identity validation, and smart contract execution. HealthChainWebClient provides a web interface for patients to manage records and contracts. The system uses HAPI FHIR for document formatting, PCCH for chameleon hashing, and AFGH for proxy re-encryption, built on the Java Pairing-Based Cryptography (jPBC) library. The implementation supports redactable blocks and secure data exchange via smart contracts, with future integration planned into platforms like Hyperledger Fabric. | Y20: To enable secure, patient-controlled sharing of health data and improve interoperability | Z20: Tracking is essential to consolidate fragmented patient health records, ensure data integrity, and enable secure, patient-controlled data sharing. It aims to restore patient agency, improve care coordination, and support longitudinal health data aggregation. By using smart contracts and cryptographic identities, the system ensures that only authorized entities can access sensitive information, thereby enhancing privacy and compliance with legal standards. | AA20: Tracking is essential to consolidate fragmented patient health records, ensure data integrity, and enable secure, patient-controlled data sharing. It aims to restore patient agency, improve care coordination, and support longitudinal health data aggregation. By using smart contracts and cryptographic identities, the system ensures that only authorized entities can access sensitive information, thereby enhancing privacy and compliance with legal standards. | AB20: Yes; via smart contracts and cryptographic identities | AC20: Yes, the framework supports responsibility attribution through cryptographic identities and smart contracts. Each patient and authorized entity is assigned public-private key pairs, and transactions are signed and logged immutably. This enables traceability and accountability in case of data leakage or unauthorized access. | AD20: Yes, the framework supports responsibility attribution through cryptographic identities and smart contracts. Each patient and authorized entity is assigned public-private key pairs, and transactions are signed and logged immutably. This enables traceability and accountability in case of data leakage or unauthorized access. | AE20: False – Proof-of-concept only | AF20: TRUE | AG20: The study includes a proof-of-concept implementation and performance evaluation across multiple configurations. | AH20: True – Novel mixed-block architecture and 2PD scheme | AI20: TRUE | AJ20: The paper introduces a novel framework (HealthChain) with redactable blocks and a 2-party proxy re-encryption scheme. | AK20: True – Performance evaluation of 16 configurations | AL20: TRUE | AM20: Structured experiments were conducted measuring transmission size, latency, processing time, and smart contract execution. | AN20: False – No industrial validation | AO20: FALSE | AP20: The evaluation was conducted in a controlled environment, not within an industrial or clinical setting. | AQ20: False – Not conceptual only | AR20: FALSE | AS20: The paper presents a working proof-of-concept implementation, not just a conceptual framework. | AT20: False – Not based on author opinion | AU20: FALSE | AV20: The study is based on empirical evaluation rather than solely on author experience or opinion. | AW20: Validation research | AX20: Evaluation research | AY20: Simulation as an empirical method | AZ20: Prototyping | BA20: HealthChain enables secure, patient-controlled data exchange with multiple configurations balancing performance and security | BB20: HealthChain demonstrates that blockchain can effectively support patient-centered health data exchange. The framework offers multiple configurations balancing performance and security. Static AES encryption with incremental storage (ASIN) was the fastest and least bandwidth-intensive, while dynamic PRE encryption with server-side support (PDIY) provided the highest security. The study concludes that implementers must choose configurations based on their specific needs for speed, security, and scalability. | BC20: HealthChain demonstrates that blockchain can effectively support patient-centered health data exchange. The framework offers multiple configurations balancing performance and security. Static AES encryption with incremental storage (ASIN) was the fastest and least bandwidth-intensive, while dynamic PRE encryption with server-side support (PDIY) provided the highest security. The study concludes that implementers must choose configurations based on their specific needs for speed, security, and scalability. | BD20: No real-world deployment; limited to simulation and proof-of-concept | BE20: The evaluation was limited to AES-128 and EC-256 cryptographic schemes, with small experimental files that may not reflect real-world EHR data. Only one smart contract was tested, and server-side encryption was only implemented in dynamic mode. These constraints may affect generalizability and performance in production environments. | BF20: The evaluation was limited to AES-128 and EC-256 cryptographic schemes, with small experimental files that may not reflect real-world EHR data. Only one smart contract was tested, and server-side encryption was only implemented in dynamic mode. These constraints may affect generalizability and performance in production environments. | BG20: Strong emphasis on patient agency and compliance with HIPAA | BH20: The article provides a comprehensive technical and experimental analysis of a blockchain-based health data exchange framework. It includes detailed implementation and performance metrics, making it suitable for further development and integration into existing systems.
A21: 2-s2.0-85075131159 | B21: =VLOOKUP(A21,'Data Set'!A:C,2,FALSE) -> rayyan-218688212 | C21: =VLOOKUP(A21,'Data Set'!A:D,3,FALSE) -> Backward.1 | D21: P020 | E21: 10.1109/TrustCom/BigDataSE.2019.00085 | F21: MedBloc: A Blockchain-based Secure EHR System for Sharing and Accessing Medical Data | G21: 2019 | H21: To present MedBloc, a blockchain-based EHR system for secure sharing and access control in New Zealand | I21: To present MedBloc, a blockchain-based secure Electronic Health Record (EHR) system designed to enable patients and healthcare providers in New Zealand to access and share health records in a privacy-preserving and usable manner. | J21: To present MedBloc, a blockchain-based secure Electronic Health Record (EHR) system designed to enable patients and healthcare providers in New Zealand to access and share health records in a privacy-preserving and usable manner. | K21: blockchain, EHR sharing, smart contracts, consent management, interoperability | L21: Permissioned blockchain with smart contracts for access control; authentication server for key management; HL7 FHIR for interoperability | M21: The study addresses the fragmented and non-unified health IT landscape in New Zealand, where disparate systems hinder efficient sharing of Electronic Health Records (EHRs). MedBloc is proposed as a blockchain-based solution that empowers patients to manage and share their health data securely. The system uses encryption and smart contracts to enforce access control and consent management. It introduces an authentication server and certificate authority to manage cryptographic material and identities. Compared to existing systems like MedRec and FHIRChain, MedBloc offers enhanced usability, privacy, and scalability through its permissioned blockchain architecture and integration of cryptographic techniques. | N21: The study addresses the fragmented and non-unified health IT landscape in New Zealand, where disparate systems hinder efficient sharing of Electronic Health Records (EHRs). MedBloc is proposed as a blockchain-based solution that empowers patients to manage and share their health data securely. The system uses encryption and smart contracts to enforce access control and consent management. It introduces an authentication server and certificate authority to manage cryptographic material and identities. Compared to existing systems like MedRec and FHIRChain, MedBloc offers enhanced usability, privacy, and scalability through its permissioned blockchain architecture and integration of cryptographic techniques. | O21: Patient health records and access permissions | P21: Health data and Electronic Health Records (EHRs) | Q21: Health data and Electronic Health Records (EHRs) | R21: Server-centered | S21: server-centered | T21: Server-centered | U21: =_xlfn.XLOOKUP(A21,ArticlesArchitecture[[#This Row],[Article ID]],ArticlesArchitecture[[#This Row],[Theme (final decision)]]) -> Hybrid (user-centered and server-centered) | V21: Hyperledger Fabric, HL7 FHIR, Smart Contracts, AES, ECC, Java, CouchDB | W21: MedBloc is implemented using Hyperledger Fabric, a permissioned blockchain platform that employs Practical Byzantine Fault Tolerance (PBFT) for consensus. The system includes smart contracts for access control, an authentication server for managing cryptographic material, and a certificate authority for identity verification. Cryptographic operations are handled using CryptoJS, a JavaScript library, and data is stored using CouchDB. The architecture supports CRUD operations via client services tailored for patients and healthcare providers, enabling secure data sharing and consent management. | X21: MedBloc is implemented using Hyperledger Fabric, a permissioned blockchain platform that employs Practical Byzantine Fault Tolerance (PBFT) for consensus. The system includes smart contracts for access control, an authentication server for managing cryptographic material, and a certificate authority for identity verification. Cryptographic operations are handled using CryptoJS, a JavaScript library, and data is stored using CouchDB. The architecture supports CRUD operations via client services tailored for patients and healthcare providers, enabling secure data sharing and consent management. | Y21: To enable secure, patient-consented sharing of EHRs across healthcare providers | Z21: Tracking is necessary to ensure secure, privacy-preserving access to health records, enable patient-driven consent management, and provide a longitudinal view of patient health. It aims to unify New Zealand’s health IT systems, improve data availability, and empower patients to control their health information. | AA21: Tracking is necessary to ensure secure, privacy-preserving access to health records, enable patient-driven consent management, and provide a longitudinal view of patient health. It aims to unify New Zealand’s health IT systems, improve data availability, and empower patients to control their health information. | AB21: Yes; via smart contracts and consent lists | AC21: Yes, the system enables responsibility attribution through the use of digital certificates issued by a Certificate Authority. These certificates are attached to transactions, allowing verification of sender identity and ensuring accountability in case of data leakage. | AD21: Yes, the system enables responsibility attribution through the use of digital certificates issued by a Certificate Authority. These certificates are attached to transactions, allowing verification of sender identity and ensuring accountability in case of data leakage. | AE21: False – No real-world deployment | AF21: TRUE | AG21: The system was implemented using Hyperledger Fabric and tested for performance, indicating real-world application. | AH21: True – Novel integration of blockchain with FHIR and consent management | AI21: TRUE | AJ21: The paper introduces MedBloc, a novel blockchain-based EHR system with unique features such as consent management and authentication server integration. | AK21: True – Performance benchmarking on Hyperledger Fabric | AL21: TRUE | AM21: Empirical evaluation was conducted through performance benchmarks measuring throughput and latency. | AN21: False – No industrial validation | AO21: FALSE | AP21: There is no evidence of industrial validation or deployment in a live healthcare setting. | AQ21: False – Not conceptual only | AR21: FALSE | AS21: The paper presents a fully implemented system rather than a conceptual framework. | AT21: False – Not based on author opinion | AU21: FALSE | AV21: The study is based on technical implementation and empirical evaluation, not solely on author experience. | AW21: Validation research | AX21: Evaluation research | AY21: Simulation as an empirical method | AZ21: Prototyping | BA21: MedBloc enables secure, patient-consented EHR sharing with interoperability and access control | BB21: MedBloc successfully demonstrates how blockchain can be used to build a secure, patient-driven EHR system. It enables encrypted storage, consent-based access control, and efficient data sharing. Performance benchmarks show that access control rules have negligible impact on latency and throughput, and encryption/decryption times scale linearly with file size. | BC21: MedBloc successfully demonstrates how blockchain can be used to build a secure, patient-driven EHR system. It enables encrypted storage, consent-based access control, and efficient data sharing. Performance benchmarks show that access control rules have negligible impact on latency and throughput, and encryption/decryption times scale linearly with file size. | BD21: Limited to simulation; no real-world deployment | BE21: The encryption and decryption performance was tested using JavaScript, which may not be optimal for production environments. The access control rules tested were of low complexity and may not reflect real-world scenarios. | BF21: The encryption and decryption performance was tested using JavaScript, which may not be optimal for production environments. The access control rules tested were of low complexity and may not reflect real-world scenarios. | BG21: Strong emphasis on New Zealand healthcare context and FHIR compliance | BH21: The study is focused on the New Zealand healthcare system but claims applicability to other countries. The system is fully implemented and tested, distinguishing it from conceptual proposals.
A22: 2-s2.0-85075631977 | B22: =VLOOKUP(A22,'Data Set'!A:C,2,FALSE) -> rayyan-218688425 | C22: =VLOOKUP(A22,'Data Set'!A:D,3,FALSE) -> Backward.1 | D22: P021 | E22: 10.1109/ACCESS.2019.2952942 | F22: MedChain: A Design of Blockchain-Based System for Medical Records Access and Permissions Management | G22: 2019 | H22: To design MedChain, a blockchain-based system for secure, interoperable access to EMRs with timed smart contracts and incentive mechanism | I22: To design and evaluate a blockchain-based system, MedChain, for managing electronic medical records (EMRs) that ensures secure, interoperable, and efficient access while maintaining patient privacy. | J22: To design and evaluate a blockchain-based system, MedChain, for managing electronic medical records (EMRs) that ensures secure, interoperable, and efficient access while maintaining patient privacy. | K22: EMR access, blockchain, smart contracts, proxy re-encryption, PoA consensus | L22: Uses Ethereum smart contracts to manage EMR access; proxy re-encryption for third-party access; PoA consensus with provider degree-based incentives | M22: The study addresses the healthcare domain, focusing on the challenge of fragmented and insecure access to electronic medical records. It proposes MedChain, a blockchain-based framework that integrates timed smart contracts, advanced encryption, and a novel incentive mechanism to manage EMRs securely and efficiently. The system is built atop existing provider databases and uses Proof of Authority consensus to ensure fairness and sustainability. Comparative analysis with traditional relational databases demonstrates MedChain’s ability to handle large datasets with low latency and improved security. | N22: The study addresses the healthcare domain, focusing on the challenge of fragmented and insecure access to electronic medical records. It proposes MedChain, a blockchain-based framework that integrates timed smart contracts, advanced encryption, and a novel incentive mechanism to manage EMRs securely and efficiently. The system is built atop existing provider databases and uses Proof of Authority consensus to ensure fairness and sustainability. Comparative analysis with traditional relational databases demonstrates MedChain’s ability to handle large datasets with low latency and improved security. | O22: EMR access logs, permissions, and encrypted records | P22: Electronic medical records and access logs | Q22: Electronic medical records and access logs | R22: Server-centered | S22: server-centered | T22: Server-centered | U22: =_xlfn.XLOOKUP(A22,ArticlesArchitecture[[#This Row],[Article ID]],ArticlesArchitecture[[#This Row],[Theme (final decision)]]) -> Server-centered | V22: Ethereum, Solidity, Truffle, web3.js, Apache JMeter, OpenMRS dataset, proxy re-encryption | W22: MedChain is implemented using a permissioned Ethereum blockchain with smart contracts written in Solidity and deployed via Truffle. It integrates GoEthereum clients for node access, a Python-based Records Evaluation Manager (REM) for assessing provider node degrees, and a GoLang-based DB Manager for database interaction. The system uses SHA-256 hashing for integrity, symmetric and proxy re-encryption for security, and web3.js for web interface communication. The architecture combines blockchain with relational databases to balance performance and security, with on-chain contracts managing permissions and access control. | X22: MedChain is implemented using a permissioned Ethereum blockchain with smart contracts written in Solidity and deployed via Truffle. It integrates GoEthereum clients for node access, a Python-based Records Evaluation Manager (REM) for assessing provider node degrees, and a GoLang-based DB Manager for database interaction. The system uses SHA-256 hashing for integrity, symmetric and proxy re-encryption for security, and web3.js for web interface communication. The architecture combines blockchain with relational databases to balance performance and security, with on-chain contracts managing permissions and access control. | Y22: To ensure secure, auditable, and policy-driven access to EMRs across providers | Z22: Tracking is essential to ensure data integrity, auditability, and secure access to EMRs. It enables monitoring of all interactions with medical records, supports privacy enforcement through smart contracts, and facilitates accountability by logging access events. The tracking mechanism also aids in validating transactions and maintaining trust among participants in the blockchain network. | AA22: Tracking is essential to ensure data integrity, auditability, and secure access to EMRs. It enables monitoring of all interactions with medical records, supports privacy enforcement through smart contracts, and facilitates accountability by logging access events. The tracking mechanism also aids in validating transactions and maintaining trust among participants in the blockchain network. | AB22: Yes; smart contracts enforce access levels and log all transactions | AC22: Yes, the system enables responsibility attribution through detailed logging of access events and the use of smart contracts that record participant identities and roles. The Nodes Consensus Contract (NCC) and Logs Contract (LC) collectively ensure traceability and accountability in case of data misuse or leakage. | AD22: Yes, the system enables responsibility attribution through detailed logging of access events and the use of smart contracts that record participant identities and roles. The Nodes Consensus Contract (NCC) and Logs Contract (LC) collectively ensure traceability and accountability in case of data misuse or leakage. | AE22: True. Implemented and tested with OpenMRS dataset | AF22: TRUE | AG22: The system is implemented and evaluated using real-world datasets and platforms such as Ethereum and OpenMRS. | AH22: True. Novel incentive mechanism based on provider degree | AI22: TRUE | AJ22: The paper introduces a novel incentive mechanism integrated with Proof of Authority consensus for EMR management. | AK22: True. Performance evaluation with JMeter and throughput analysis | AL22: TRUE | AM22: Extensive experiments are conducted measuring response time, throughput, and communication overhead. | AN22: False. No industrial deployment | AO22: FALSE | AP22: The evaluation is performed in a simulated environment, not within an actual industrial healthcare setting. | AQ22: False. Full system implemented | AR22: FALSE | AS22: The paper presents a fully implemented system with experimental validation, not just a conceptual framework. | AT22: False. Not based on personal experience | AU22: FALSE | AV22: The study is based on empirical data and system implementation, not solely on author opinions or experiences. | AW22: Evaluation research | AX22: Evaluation research | AY22: Prototyping | AZ22: Controlled experiment with practitioners | BA22: MedChain enables secure, policy-driven EMR access with low latency and provider fairness | BB22: MedChain effectively manages EMRs with enhanced privacy, security, and interoperability. It performs comparably to traditional systems in terms of latency and throughput while offering superior data integrity and access control. The incentive mechanism ensures fair participation among providers, and the system is scalable for large datasets. | BC22: MedChain effectively manages EMRs with enhanced privacy, security, and interoperability. It performs comparably to traditional systems in terms of latency and throughput while offering superior data integrity and access control. The incentive mechanism ensures fair participation among providers, and the system is scalable for large datasets. | BD22: Limited to prototype; no industrial deployment; incentive model not tested in real-world | BE22: The system was not validated in a live industrial healthcare environment. The incentive mechanism’s long-term sustainability and real-world adoption remain untested. | BF22: The system was not validated in a live industrial healthcare environment. The incentive mechanism’s long-term sustainability and real-world adoption remain untested. | BG22: Uses degree-based PoA to balance block creation | BH22: The article provides a comprehensive technical and experimental evaluation of MedChain, making it a strong candidate for inclusion in studies on blockchain applications in healthcare.
